{
  "localizations" : {
    "Sign up with Apple" : [
      {
        "target" : "Mit Apple anmelden",
        "filename" : "Localizable.strings",
        "language" : "de"
      },
      {
        "target" : "הרשמה באמצעות Apple",
        "filename" : "Localizable.strings",
        "language" : "he"
      },
      {
        "target" : "Sign up with Apple",
        "filename" : "Localizable.strings",
        "language" : "en_AU"
      },
      {
        "target" : "التسجيل باستخدام Apple",
        "filename" : "Localizable.strings",
        "language" : "ar"
      },
      {
        "target" : "Εγγραφή μέσω Apple",
        "filename" : "Localizable.strings",
        "language" : "el"
      },
      {
        "target" : "Appleでサインアップ",
        "filename" : "Localizable.strings",
        "language" : "ja"
      },
      {
        "target" : "Sign up with Apple",
        "filename" : "Localizable.strings",
        "language" : "en"
      },
      {
        "target" : "Реєстрація з Apple",
        "filename" : "Localizable.strings",
        "language" : "uk"
      },
      {
        "target" : "Registrarse con Apple",
        "filename" : "Localizable.strings",
        "language" : "es_419"
      },
      {
        "target" : "通过Apple注册",
        "filename" : "Localizable.strings",
        "language" : "zh_CN"
      },
      {
        "target" : "Registrarse con Apple",
        "filename" : "Localizable.strings",
        "language" : "es"
      },
      {
        "target" : "Tilmeld dig med Apple",
        "filename" : "Localizable.strings",
        "language" : "da"
      },
      {
        "target" : "Iscriviti con Apple",
        "filename" : "Localizable.strings",
        "language" : "it"
      },
      {
        "target" : "Registrácia cez Apple",
        "filename" : "Localizable.strings",
        "language" : "sk"
      },
      {
        "target" : "Registar‑se com a Apple",
        "filename" : "Localizable.strings",
        "language" : "pt_PT"
      },
      {
        "target" : "Daftar dengan Apple",
        "filename" : "Localizable.strings",
        "language" : "ms"
      },
      {
        "target" : "Registrera dig med Apple",
        "filename" : "Localizable.strings",
        "language" : "sv"
      },
      {
        "target" : "Zaregistrovat se přes Apple",
        "filename" : "Localizable.strings",
        "language" : "cs"
      },
      {
        "target" : "Apple로 등록",
        "filename" : "Localizable.strings",
        "language" : "ko"
      },
      {
        "target" : "Registrer deg med Apple",
        "filename" : "Localizable.strings",
        "language" : "no"
      },
      {
        "target" : "Regisztráció az Apple-lel",
        "filename" : "Localizable.strings",
        "language" : "hu"
      },
      {
        "target" : "使用Apple註冊",
        "filename" : "Localizable.strings",
        "language" : "zh_HK"
      },
      {
        "target" : "Apple ile Kaydol",
        "filename" : "Localizable.strings",
        "language" : "tr"
      },
      {
        "target" : "Zarejestruj się, używając konta Apple",
        "filename" : "Localizable.strings",
        "language" : "pl"
      },
      {
        "target" : "使用Apple註冊",
        "filename" : "Localizable.strings",
        "language" : "zh_TW"
      },
      {
        "target" : "Sign up with Apple",
        "filename" : "Localizable.strings",
        "language" : "en_GB"
      },
      {
        "target" : "Đăng ký bằng Apple",
        "filename" : "Localizable.strings",
        "language" : "vi"
      },
      {
        "target" : "Зарегистрироваться с Apple",
        "filename" : "Localizable.strings",
        "language" : "ru"
      },
      {
        "target" : "Inscription avec Apple",
        "filename" : "Localizable.strings",
        "language" : "fr_CA"
      },
      {
        "target" : "S’inscrire avec Apple",
        "filename" : "Localizable.strings",
        "language" : "fr"
      },
      {
        "target" : "Rekisteröidy Applella",
        "filename" : "Localizable.strings",
        "language" : "fi"
      },
      {
        "target" : "Daftar dengan Apple",
        "filename" : "Localizable.strings",
        "language" : "id"
      },
      {
        "target" : "Meld je aan met Apple",
        "filename" : "Localizable.strings",
        "language" : "nl"
      },
      {
        "target" : "ลงทะเบียนด้วย Apple",
        "filename" : "Localizable.strings",
        "language" : "th"
      },
      {
        "target" : "Registre-se com a Apple",
        "filename" : "Localizable.strings",
        "language" : "pt"
      },
      {
        "target" : "Înscrieți‑vă cu Apple",
        "filename" : "Localizable.strings",
        "language" : "ro"
      },
      {
        "target" : "Registracija s Appleom",
        "filename" : "Localizable.strings",
        "language" : "hr"
      },
      {
        "target" : "Apple से साइन अप करें",
        "filename" : "Localizable.strings",
        "language" : "hi"
      },
      {
        "target" : "Registrar-se a Apple",
        "filename" : "Localizable.strings",
        "language" : "ca"
      }
    ],
    "Continue with Apple" : [
      {
        "target" : "Mit Apple fortfahren",
        "filename" : "Localizable.strings",
        "language" : "de"
      },
      {
        "target" : "המשך עם Apple",
        "filename" : "Localizable.strings",
        "language" : "he"
      },
      {
        "target" : "Continue with Apple",
        "filename" : "Localizable.strings",
        "language" : "en_AU"
      },
      {
        "target" : "الاستمرار باستخدام Apple",
        "filename" : "Localizable.strings",
        "language" : "ar"
      },
      {
        "target" : "Συνέχεια μέσω Apple",
        "filename" : "Localizable.strings",
        "language" : "el"
      },
      {
        "target" : "Appleで続ける",
        "filename" : "Localizable.strings",
        "language" : "ja"
      },
      {
        "target" : "Continue with Apple",
        "filename" : "Localizable.strings",
        "language" : "en"
      },
      {
        "target" : "Використати Apple",
        "filename" : "Localizable.strings",
        "language" : "uk"
      },
      {
        "target" : "Continuar con Apple",
        "filename" : "Localizable.strings",
        "language" : "es_419"
      },
      {
        "target" : "通过Apple继续",
        "filename" : "Localizable.strings",
        "language" : "zh_CN"
      },
      {
        "target" : "Continuar con Apple",
        "filename" : "Localizable.strings",
        "language" : "es"
      },
      {
        "target" : "Fortsæt med Apple",
        "filename" : "Localizable.strings",
        "language" : "da"
      },
      {
        "target" : "Continua con Apple",
        "filename" : "Localizable.strings",
        "language" : "it"
      },
      {
        "target" : "Pokračovať cez Apple",
        "filename" : "Localizable.strings",
        "language" : "sk"
      },
      {
        "target" : "Continuar com a Apple",
        "filename" : "Localizable.strings",
        "language" : "pt_PT"
      },
      {
        "target" : "Teruskan dengan Apple",
        "filename" : "Localizable.strings",
        "language" : "ms"
      },
      {
        "target" : "Fortsätt med Apple",
        "filename" : "Localizable.strings",
        "language" : "sv"
      },
      {
        "target" : "Pokračovat přes Apple",
        "filename" : "Localizable.strings",
        "language" : "cs"
      },
      {
        "target" : "Apple로 계속하기",
        "filename" : "Localizable.strings",
        "language" : "ko"
      },
      {
        "target" : "Fortsett med Apple",
        "filename" : "Localizable.strings",
        "language" : "no"
      },
      {
        "target" : "Folytatás az Apple-lel",
        "filename" : "Localizable.strings",
        "language" : "hu"
      },
      {
        "target" : "使用Apple繼續",
        "filename" : "Localizable.strings",
        "language" : "zh_HK"
      },
      {
        "target" : "Apple ile Devam Et",
        "filename" : "Localizable.strings",
        "language" : "tr"
      },
      {
        "target" : "Kontynuuj, używając konta Apple",
        "filename" : "Localizable.strings",
        "language" : "pl"
      },
      {
        "target" : "透過Apple繼續",
        "filename" : "Localizable.strings",
        "language" : "zh_TW"
      },
      {
        "target" : "Continue with Apple",
        "filename" : "Localizable.strings",
        "language" : "en_GB"
      },
      {
        "target" : "Tiếp tục với Apple",
        "filename" : "Localizable.strings",
        "language" : "vi"
      },
      {
        "target" : "Продолжить с Apple",
        "filename" : "Localizable.strings",
        "language" : "ru"
      },
      {
        "target" : "Continuer avec Apple",
        "filename" : "Localizable.strings",
        "language" : "fr_CA"
      },
      {
        "target" : "Continuer avec Apple",
        "filename" : "Localizable.strings",
        "language" : "fr"
      },
      {
        "target" : "Jatka Applella",
        "filename" : "Localizable.strings",
        "language" : "fi"
      },
      {
        "target" : "Lanjutkan dengan Apple",
        "filename" : "Localizable.strings",
        "language" : "id"
      },
      {
        "target" : "Ga door met Apple",
        "filename" : "Localizable.strings",
        "language" : "nl"
      },
      {
        "target" : "ดำเนินการต่อด้วย Apple",
        "filename" : "Localizable.strings",
        "language" : "th"
      },
      {
        "target" : "Continuar com a Apple",
        "filename" : "Localizable.strings",
        "language" : "pt"
      },
      {
        "target" : "Continuați cu Apple",
        "filename" : "Localizable.strings",
        "language" : "ro"
      },
      {
        "target" : "Nastavi koristeći Apple",
        "filename" : "Localizable.strings",
        "language" : "hr"
      },
      {
        "target" : "Apple से जारी रखें",
        "filename" : "Localizable.strings",
        "language" : "hi"
      },
      {
        "target" : "Continuar amb Apple",
        "filename" : "Localizable.strings",
        "language" : "ca"
      }
    ],
    "Sign in with Apple" : [
      {
        "target" : "Mit Apple anmelden",
        "filename" : "Localizable.strings",
        "language" : "de"
      },
      {
        "target" : "התחברות באמצעות Apple",
        "filename" : "Localizable.strings",
        "language" : "he"
      },
      {
        "target" : "Sign in with Apple",
        "filename" : "Localizable.strings",
        "language" : "en_AU"
      },
      {
        "target" : "تسجيل الدخول باستخدام Apple",
        "filename" : "Localizable.strings",
        "language" : "ar"
      },
      {
        "target" : "Σύνδεση μέσω Apple",
        "filename" : "Localizable.strings",
        "language" : "el"
      },
      {
        "target" : "Appleでサインイン",
        "filename" : "Localizable.strings",
        "language" : "ja"
      },
      {
        "target" : "Sign in with Apple",
        "filename" : "Localizable.strings",
        "language" : "en"
      },
      {
        "target" : "Вхід з Apple",
        "filename" : "Localizable.strings",
        "language" : "uk"
      },
      {
        "target" : "Iniciar sesión con Apple",
        "filename" : "Localizable.strings",
        "language" : "es_419"
      },
      {
        "target" : "通过Apple登录",
        "filename" : "Localizable.strings",
        "language" : "zh_CN"
      },
      {
        "target" : "Iniciar sesión con Apple",
        "filename" : "Localizable.strings",
        "language" : "es"
      },
      {
        "target" : "Log ind med Apple",
        "filename" : "Localizable.strings",
        "language" : "da"
      },
      {
        "target" : "Accedi con Apple",
        "filename" : "Localizable.strings",
        "language" : "it"
      },
      {
        "target" : "Prihlásenie cez Apple",
        "filename" : "Localizable.strings",
        "language" : "sk"
      },
      {
        "target" : "Iniciar sessão com a Apple",
        "filename" : "Localizable.strings",
        "language" : "pt_PT"
      },
      {
        "target" : "Daftar masuk dengan Apple",
        "filename" : "Localizable.strings",
        "language" : "ms"
      },
      {
        "target" : "Logga in med Apple",
        "filename" : "Localizable.strings",
        "language" : "sv"
      },
      {
        "target" : "Přihlášení přes Apple",
        "filename" : "Localizable.strings",
        "language" : "cs"
      },
      {
        "target" : "Apple로 로그인",
        "filename" : "Localizable.strings",
        "language" : "ko"
      },
      {
        "target" : "Logg på med Apple",
        "filename" : "Localizable.strings",
        "language" : "no"
      },
      {
        "target" : "Bejelentkezés az Apple-lel",
        "filename" : "Localizable.strings",
        "language" : "hu"
      },
      {
        "target" : "使用Apple登入",
        "filename" : "Localizable.strings",
        "language" : "zh_HK"
      },
      {
        "target" : "Apple ile Giriş Yap",
        "filename" : "Localizable.strings",
        "language" : "tr"
      },
      {
        "target" : "Funkcja Zaloguj się, używając konta Apple",
        "filename" : "Localizable.strings",
        "language" : "pl"
      },
      {
        "target" : "使用Apple登入",
        "filename" : "Localizable.strings",
        "language" : "zh_TW"
      },
      {
        "target" : "Sign in with Apple",
        "filename" : "Localizable.strings",
        "language" : "en_GB"
      },
      {
        "target" : "Đăng nhập bằng Apple",
        "filename" : "Localizable.strings",
        "language" : "vi"
      },
      {
        "target" : "Вход с Apple",
        "filename" : "Localizable.strings",
        "language" : "ru"
      },
      {
        "target" : "Connexion avec Apple",
        "filename" : "Localizable.strings",
        "language" : "fr_CA"
      },
      {
        "target" : "Se connecter avec Apple",
        "filename" : "Localizable.strings",
        "language" : "fr"
      },
      {
        "target" : "Kirjaudu sisään Applella",
        "filename" : "Localizable.strings",
        "language" : "fi"
      },
      {
        "target" : "Masuk dengan Apple",
        "filename" : "Localizable.strings",
        "language" : "id"
      },
      {
        "target" : "Log in met Apple",
        "filename" : "Localizable.strings",
        "language" : "nl"
      },
      {
        "target" : "ลงชื่อเข้าด้วย Apple",
        "filename" : "Localizable.strings",
        "language" : "th"
      },
      {
        "target" : "Iniciar sessão com a Apple",
        "filename" : "Localizable.strings",
        "language" : "pt"
      },
      {
        "target" : "Autentificați‑vă cu Apple",
        "filename" : "Localizable.strings",
        "language" : "ro"
      },
      {
        "target" : "Prijava s Appleom",
        "filename" : "Localizable.strings",
        "language" : "hr"
      },
      {
        "target" : "Apple से साइन इन करें",
        "filename" : "Localizable.strings",
        "language" : "hi"
      },
      {
        "target" : "Inicia sessió amb Apple",
        "filename" : "Localizable.strings",
        "language" : "ca"
      }
    ],
    "Account upgrades are not supported on macOS." : [
      {
        "target" : "Account-Upgrades werden in macOS nicht unterstützt.",
        "filename" : "Localizable.strings",
        "language" : "de"
      },
      {
        "target" : "שדרוג החשבון לא נתמך ב-macOS.",
        "filename" : "Localizable.strings",
        "language" : "he"
      },
      {
        "target" : "Account upgrades are not supported on macOS.",
        "filename" : "Localizable.strings",
        "language" : "en_AU"
      },
      {
        "target" : "ترقيات الحساب غير مدعومة على macOS.",
        "filename" : "Localizable.strings",
        "language" : "ar"
      },
      {
        "target" : "Οι αναβαθμίσεις λογαριασμών δεν υποστηρίζονται στο macOS.",
        "filename" : "Localizable.strings",
        "language" : "el"
      },
      {
        "target" : "アカウントのアップグレードはmacOSでは対応していません。",
        "filename" : "Localizable.strings",
        "language" : "ja"
      },
      {
        "target" : "Account upgrades are not supported on macOS.",
        "filename" : "Localizable.strings",
        "language" : "en"
      },
      {
        "target" : "Оновлення облікових записів не підтримується на macOS.",
        "filename" : "Localizable.strings",
        "language" : "uk"
      },
      {
        "target" : "macOS no es compatible con las actualizaciones de cuentas.",
        "filename" : "Localizable.strings",
        "language" : "es_419"
      },
      {
        "target" : "macOS上不支持帐户升级。",
        "filename" : "Localizable.strings",
        "language" : "zh_CN"
      },
      {
        "target" : "macOS no es compatible con las actualizaciones de cuenta.",
        "filename" : "Localizable.strings",
        "language" : "es"
      },
      {
        "target" : "Kontoopgraderinger understøttes ikke på macOS.",
        "filename" : "Localizable.strings",
        "language" : "da"
      },
      {
        "target" : "Gli aggiornamenti dell'account non sono supportati su macOS.",
        "filename" : "Localizable.strings",
        "language" : "it"
      },
      {
        "target" : "Upgradovanie účtov nie je podporované v systéme macOS.",
        "filename" : "Localizable.strings",
        "language" : "sk"
      },
      {
        "target" : "As atualizações de contas não são suportadas no macOS.",
        "filename" : "Localizable.strings",
        "language" : "pt_PT"
      },
      {
        "target" : "Naik taraf akaun tidak disokong pada macOS.",
        "filename" : "Localizable.strings",
        "language" : "ms"
      },
      {
        "target" : "Kontouppgraderingar stöds inte i macOS.",
        "filename" : "Localizable.strings",
        "language" : "sv"
      },
      {
        "target" : "Upgradování účtů není na macOS podporováno.",
        "filename" : "Localizable.strings",
        "language" : "cs"
      },
      {
        "target" : "macOS에서는 계정 업그레이드가 지원되지 않습니다.",
        "filename" : "Localizable.strings",
        "language" : "ko"
      },
      {
        "target" : "Kontooppgradering støttes ikke på macOS.",
        "filename" : "Localizable.strings",
        "language" : "no"
      },
      {
        "target" : "A fiókok bővítése nem támogatott macOS rendszerben.",
        "filename" : "Localizable.strings",
        "language" : "hu"
      },
      {
        "target" : "macOS不支援帳户升級。",
        "filename" : "Localizable.strings",
        "language" : "zh_HK"
      },
      {
        "target" : "Hesap yükseltmeleri macOS’te desteklenmiyor.",
        "filename" : "Localizable.strings",
        "language" : "tr"
      },
      {
        "target" : "Konwersja kont nie jest obsługiwana w systemie macOS.",
        "filename" : "Localizable.strings",
        "language" : "pl"
      },
      {
        "target" : "macOS不支援帳號升級。",
        "filename" : "Localizable.strings",
        "language" : "zh_TW"
      },
      {
        "target" : "Account upgrades are not supported on macOS.",
        "filename" : "Localizable.strings",
        "language" : "en_GB"
      },
      {
        "target" : "Không hỗ trợ nâng cấp tài khoản trên macOS.",
        "filename" : "Localizable.strings",
        "language" : "vi"
      },
      {
        "target" : "Обновления учетной записи не поддерживаются в macOS.",
        "filename" : "Localizable.strings",
        "language" : "ru"
      },
      {
        "target" : "Les mises à niveau de compte ne sont pas prises en charge sous macOS.",
        "filename" : "Localizable.strings",
        "language" : "fr_CA"
      },
      {
        "target" : "Les mises à niveau de compte ne sont pas prises en charge sur macOS.",
        "filename" : "Localizable.strings",
        "language" : "fr"
      },
      {
        "target" : "macOS ei tue tilin päivitystä.",
        "filename" : "Localizable.strings",
        "language" : "fi"
      },
      {
        "target" : "Peningkatan akun tidak didukung di macOS.",
        "filename" : "Localizable.strings",
        "language" : "id"
      },
      {
        "target" : "Account­upgrades worden niet ondersteund op macOS.",
        "filename" : "Localizable.strings",
        "language" : "nl"
      },
      {
        "target" : "ไม่รองรับการอัปเกรดบัญชีบน macOS",
        "filename" : "Localizable.strings",
        "language" : "th"
      },
      {
        "target" : "O macOS não é compatível com atualizações de conta.",
        "filename" : "Localizable.strings",
        "language" : "pt"
      },
      {
        "target" : "Actualizările conturilor nu sunt permise de pe macOS.",
        "filename" : "Localizable.strings",
        "language" : "ro"
      },
      {
        "target" : "Nadogradnje računa nisu podržane u sustavu macOS.",
        "filename" : "Localizable.strings",
        "language" : "hr"
      },
      {
        "target" : "खाता अपग्रेड करना macOS पर समर्थित नहीं है।",
        "filename" : "Localizable.strings",
        "language" : "hi"
      },
      {
        "target" : "Les actualitzacions de compte no són compatibles amb el macOS.",
        "filename" : "Localizable.strings",
        "language" : "ca"
      }
    ]
  },
  "bundlePath" : "\/System\/iOSSupport\/System\/Library\/Frameworks\/AuthenticationServices.framework",
  "framework" : "AuthenticationServices.framework"
}