{
  "localizations" : {
    "found.item.video" : [
      {
        "target" : "Video eines AirTag, das sich um seine Achse dreht",
        "filename" : "Accessibility-B389.strings",
        "language" : "de"
      },
      {
        "target" : "סרטון של AirTag מסתובב מצד לצד",
        "filename" : "Accessibility-B389.strings",
        "language" : "he"
      },
      {
        "target" : "Video of AirTag turning side to side",
        "filename" : "Accessibility-B389.strings",
        "language" : "en_AU"
      },
      {
        "target" : "فيديو تدوير AirTag من جانب إلى آخر",
        "filename" : "Accessibility-B389.strings",
        "language" : "ar"
      },
      {
        "target" : "Βίντεο AirTag που κουνιέται πέρα-δώθε",
        "filename" : "Accessibility-B389.strings",
        "language" : "el"
      },
      {
        "target" : "回転してエアタグの表と裏を見せているビデオ",
        "filename" : "Accessibility-B389.strings",
        "language" : "ja"
      },
      {
        "target" : "Video of AirTag turning side-to-side",
        "filename" : "Accessibility-B389.strings",
        "language" : "en"
      },
      {
        "target" : "Відео тега AirTag, який обертається з боку в бік",
        "filename" : "Accessibility-B389.strings",
        "language" : "uk"
      },
      {
        "target" : "Video de un AirTag girando horizontalmente",
        "filename" : "Accessibility-B389.strings",
        "language" : "es_419"
      },
      {
        "target" : "AirTag左右翻转的视频",
        "filename" : "Accessibility-B389.strings",
        "language" : "zh_CN"
      },
      {
        "target" : "Vídeo de un AirTag rotando sobre sí mismo",
        "filename" : "Accessibility-B389.strings",
        "language" : "es"
      },
      {
        "target" : "Video af AirTag, der drejer fra side til side",
        "filename" : "Accessibility-B389.strings",
        "language" : "da"
      },
      {
        "target" : "Video di un AirTag che gira su se stesso",
        "filename" : "Accessibility-B389.strings",
        "language" : "it"
      },
      {
        "target" : "Video AirTagu otáčajúceho sa zo strany na stranu",
        "filename" : "Accessibility-B389.strings",
        "language" : "sk"
      },
      {
        "target" : "Vídeo de um AirTag a rodar de um lado para o outro",
        "filename" : "Accessibility-B389.strings",
        "language" : "pt_PT"
      },
      {
        "target" : "Video AirTag berputar sisi ke sisi",
        "filename" : "Accessibility-B389.strings",
        "language" : "ms"
      },
      {
        "target" : "Video av AirTag som vrider sig från sida till sida",
        "filename" : "Accessibility-B389.strings",
        "language" : "sv"
      },
      {
        "target" : "Video s AirTagem otáčejícím se ze strany na stranu",
        "filename" : "Accessibility-B389.strings",
        "language" : "cs"
      },
      {
        "target" : "좌우로 빙글빙글 도는 AirTag 비디오",
        "filename" : "Accessibility-B389.strings",
        "language" : "ko"
      },
      {
        "target" : "Video med AirTag som dreier rundt sin egen akse",
        "filename" : "Accessibility-B389.strings",
        "language" : "no"
      },
      {
        "target" : "Videó egy ide-oda forgó AirTagről",
        "filename" : "Accessibility-B389.strings",
        "language" : "hu"
      },
      {
        "target" : "AirTag轉動的影片",
        "filename" : "Accessibility-B389.strings",
        "language" : "zh_HK"
      },
      {
        "target" : "Yan yana dönen AirTag videosu",
        "filename" : "Accessibility-B389.strings",
        "language" : "tr"
      },
      {
        "target" : "Wideo przedstawiające AirTag obracający się na boki",
        "filename" : "Accessibility-B389.strings",
        "language" : "pl"
      },
      {
        "target" : "AirTag左右翻轉的影片",
        "filename" : "Accessibility-B389.strings",
        "language" : "zh_TW"
      },
      {
        "target" : "Video of AirTag turning side to side",
        "filename" : "Accessibility-B389.strings",
        "language" : "en_GB"
      },
      {
        "target" : "Video về AirTag đang di chuyển giữa hai bên",
        "filename" : "Accessibility-B389.strings",
        "language" : "vi"
      },
      {
        "target" : "Видео вращающегося AirTag",
        "filename" : "Accessibility-B389.strings",
        "language" : "ru"
      },
      {
        "target" : "Vidéo d’un AirTag pivotant d’un côté à l’autre",
        "filename" : "Accessibility-B389.strings",
        "language" : "fr_CA"
      },
      {
        "target" : "Vidéo d’un AirTag qui pivote d’une face à l’autre",
        "filename" : "Accessibility-B389.strings",
        "language" : "fr"
      },
      {
        "target" : "Video pyörivästä AirTagista",
        "filename" : "Accessibility-B389.strings",
        "language" : "fi"
      },
      {
        "target" : "Video AirTag berputar dari satu sisi ke sisi lainnya",
        "filename" : "Accessibility-B389.strings",
        "language" : "id"
      },
      {
        "target" : "Video van AirTag die van links naar rechts draait",
        "filename" : "Accessibility-B389.strings",
        "language" : "nl"
      },
      {
        "target" : "ภาพของ AirTag หมุนรอบตัวเอง",
        "filename" : "Accessibility-B389.strings",
        "language" : "th"
      },
      {
        "target" : "Vídeo de um AirTag virando de lado a lado",
        "filename" : "Accessibility-B389.strings",
        "language" : "pt"
      },
      {
        "target" : "Clip video al unui AirTag întorcându‑se de pe o parte pe alta",
        "filename" : "Accessibility-B389.strings",
        "language" : "ro"
      },
      {
        "target" : "Videozapis AirTaga kako se okreće od strane do strane",
        "filename" : "Accessibility-B389.strings",
        "language" : "hr"
      },
      {
        "target" : "AirTag के एक तरफ़ से दूसरी तरफ़ पलटने का वीडियो",
        "filename" : "Accessibility-B389.strings",
        "language" : "hi"
      },
      {
        "target" : "Vídeo d’un AirTag girant cap un costat i cap a l’altre",
        "filename" : "Accessibility-B389.strings",
        "language" : "ca"
      }
    ],
    "distance.maximum.reached" : [
      {
        "target" : "Aktuell auf der größten Distanz, kann nicht höher eingestellt werden.",
        "filename" : "Accessibility.strings",
        "language" : "de"
      },
      {
        "target" : "נמצא כעת במרחק המקסימלי. לא ניתן לשנות לערך גבוה יותר.",
        "filename" : "Accessibility.strings",
        "language" : "he"
      },
      {
        "target" : "Currently at maximum distance. Cannot adjust any higher.",
        "filename" : "Accessibility.strings",
        "language" : "en_AU"
      },
      {
        "target" : "تم بلوغ أقصى مسافة حاليًا. لا يمكن ضبطها أعلى من ذلك.",
        "filename" : "Accessibility.strings",
        "language" : "ar"
      },
      {
        "target" : "Έχει οριστεί η μέγιστη απόσταση. Δεν είναι δυνατή η περαιτέρω αύξηση.",
        "filename" : "Accessibility.strings",
        "language" : "el"
      },
      {
        "target" : "現在、最大距離です。これ以上大きくできません。",
        "filename" : "Accessibility.strings",
        "language" : "ja"
      },
      {
        "target" : "Currently at maximum distance. Cannot adjust any higher.",
        "filename" : "Accessibility.strings",
        "language" : "en"
      },
      {
        "target" : "Поточна відстань на максимумі. Неможливо зробити вище.",
        "filename" : "Accessibility.strings",
        "language" : "uk"
      },
      {
        "target" : "A la máxima distancia ahora mismo. No se puede ajustar a más.",
        "filename" : "Accessibility.strings",
        "language" : "es_419"
      },
      {
        "target" : "目前已达最大距离。无法进一步调高。",
        "filename" : "Accessibility.strings",
        "language" : "zh_CN"
      },
      {
        "target" : "Se ha alcanzado la distancia máxima. No se puede aumentar más.",
        "filename" : "Accessibility.strings",
        "language" : "es"
      },
      {
        "target" : "Maksimumdistance er nået. Kan ikke justeres højere.",
        "filename" : "Accessibility.strings",
        "language" : "da"
      },
      {
        "target" : "Distanza massima raggiunta. Non è possibile regolare più in alto.",
        "filename" : "Accessibility.strings",
        "language" : "it"
      },
      {
        "target" : "Ste na maximálnej vzdialenosti. Viac sa nedá nastaviť.",
        "filename" : "Accessibility.strings",
        "language" : "sk"
      },
      {
        "target" : "Foi atingida a distância máxima. Não é possível ajustar mais.",
        "filename" : "Accessibility.strings",
        "language" : "pt_PT"
      },
      {
        "target" : "Pada jarak maksimum sekarang. Tidak boleh dilaraskan lebih tinggi.",
        "filename" : "Accessibility.strings",
        "language" : "ms"
      },
      {
        "target" : "Vid högsta avstånd just nu. Kan inte justera högre.",
        "filename" : "Accessibility.strings",
        "language" : "sv"
      },
      {
        "target" : "Jste na maximální vzdálenosti. Víc už oddálit nelze.",
        "filename" : "Accessibility.strings",
        "language" : "cs"
      },
      {
        "target" : "현재 거리가 최대 상태이며, 더 높게 조절할 수 없습니다.",
        "filename" : "Accessibility.strings",
        "language" : "ko"
      },
      {
        "target" : "Maksimum distanse er nådd. Kan ikke justere høyere.",
        "filename" : "Accessibility.strings",
        "language" : "no"
      },
      {
        "target" : "Jelenleg a maximális távolság van beállítva. Nem állítható magasabb értékre.",
        "filename" : "Accessibility.strings",
        "language" : "hu"
      },
      {
        "target" : "目前位於最遠距離。無法再調整更多。",
        "filename" : "Accessibility.strings",
        "language" : "zh_HK"
      },
      {
        "target" : "Şu anda maksimum mesafede. Daha yükseğe ayarlanamıyor.",
        "filename" : "Accessibility.strings",
        "language" : "tr"
      },
      {
        "target" : "Odległość jest już maksymalna. Nie można jej zwiększyć.",
        "filename" : "Accessibility.strings",
        "language" : "pl"
      },
      {
        "target" : "目前位於最遠距離。無法再調整更多。",
        "filename" : "Accessibility.strings",
        "language" : "zh_TW"
      },
      {
        "target" : "Currently at maximum distance. Cannot adjust any higher.",
        "filename" : "Accessibility.strings",
        "language" : "en_GB"
      },
      {
        "target" : "Hiện đang ở khoảng cách tối đa. Không thể điều chỉnh cao hơn.",
        "filename" : "Accessibility.strings",
        "language" : "vi"
      },
      {
        "target" : "Максимальное расстояние. Перемещение дальше невозможно.",
        "filename" : "Accessibility.strings",
        "language" : "ru"
      },
      {
        "target" : "Distance maximale atteinte. Impossible de l’augmenter davantage.",
        "filename" : "Accessibility.strings",
        "language" : "fr_CA"
      },
      {
        "target" : "Distance maximale atteinte. Impossible de placer l’objet plus loin.",
        "filename" : "Accessibility.strings",
        "language" : "fr"
      },
      {
        "target" : "Tällä hetkellä enimmäisetäisyydellä. Ei voida säätää korkeammaksi.",
        "filename" : "Accessibility.strings",
        "language" : "fi"
      },
      {
        "target" : "Jarak saat ini sudah maksimal. Tidak dapat disesuaikan lebih tinggi.",
        "filename" : "Accessibility.strings",
        "language" : "id"
      },
      {
        "target" : "Momenteel op maximale afstand. Kan niet verder worden aangepast.",
        "filename" : "Accessibility.strings",
        "language" : "nl"
      },
      {
        "target" : "อยู่ในระยะไกลสุดแล้ว ไม่สามารถปรับได้มากกว่านี้",
        "filename" : "Accessibility.strings",
        "language" : "th"
      },
      {
        "target" : "Atualmente na distância máxima. Não é possível ajustar acima.",
        "filename" : "Accessibility.strings",
        "language" : "pt"
      },
      {
        "target" : "A fost atinsă distanța maximă. Nu se poate ajusta mai sus.",
        "filename" : "Accessibility.strings",
        "language" : "ro"
      },
      {
        "target" : "Trenutačno na maksimalnoj udaljenosti. Ne može se podesiti na više.",
        "filename" : "Accessibility.strings",
        "language" : "hr"
      },
      {
        "target" : "वर्तमान में अधिकतम दूरी पर। इसे अधिक पर ऐडजस्ट नहीं किया जा सकता है।",
        "filename" : "Accessibility.strings",
        "language" : "hi"
      },
      {
        "target" : "S’ha ajustat a la distància màxima. Ja no es pot ajustar més.",
        "filename" : "Accessibility.strings",
        "language" : "ca"
      }
    ],
    "distance.minimum.reached" : [
      {
        "target" : "Aktuell auf der kleinsten Distanz, kann nicht niedriger eingestellt werden.",
        "filename" : "Accessibility.strings",
        "language" : "de"
      },
      {
        "target" : "נמצא כעת במרחק המינימלי. לא ניתן לשנות לערך נמוך יותר.",
        "filename" : "Accessibility.strings",
        "language" : "he"
      },
      {
        "target" : "Currently at minimum distance. Cannot adjust any lower.",
        "filename" : "Accessibility.strings",
        "language" : "en_AU"
      },
      {
        "target" : "تم بلوغ أدنى مسافة حاليًا. لا يمكن ضبطها أقل من ذلك.",
        "filename" : "Accessibility.strings",
        "language" : "ar"
      },
      {
        "target" : "Έχει οριστεί η ελάχιστη απόσταση. Δεν είναι δυνατή η περαιτέρω μείωση.",
        "filename" : "Accessibility.strings",
        "language" : "el"
      },
      {
        "target" : "現在、最小距離です。これ以上小さくできません。",
        "filename" : "Accessibility.strings",
        "language" : "ja"
      },
      {
        "target" : "Currently at minimum distance. Cannot adjust any lower.",
        "filename" : "Accessibility.strings",
        "language" : "en"
      },
      {
        "target" : "Поточна відстань на мінімумі. Неможливо зробити нижче.",
        "filename" : "Accessibility.strings",
        "language" : "uk"
      },
      {
        "target" : "A la distancia mínima ahora mismo. No se puede ajustar a menos.",
        "filename" : "Accessibility.strings",
        "language" : "es_419"
      },
      {
        "target" : "目前已达最小距离。无法进一步调低。",
        "filename" : "Accessibility.strings",
        "language" : "zh_CN"
      },
      {
        "target" : "Se ha alcanzado la distancia mínima. No se puede reducir más.",
        "filename" : "Accessibility.strings",
        "language" : "es"
      },
      {
        "target" : "Minimumdistance er nået. Kan ikke justeres lavere.",
        "filename" : "Accessibility.strings",
        "language" : "da"
      },
      {
        "target" : "Distanza minima raggiunta. Non è possibile regolare più in basso.",
        "filename" : "Accessibility.strings",
        "language" : "it"
      },
      {
        "target" : "Ste na minimálnej vzdialenosti. Menej sa nedá nastaviť.",
        "filename" : "Accessibility.strings",
        "language" : "sk"
      },
      {
        "target" : "Foi atingida a distância mínima. Não é possível ajustar menos.",
        "filename" : "Accessibility.strings",
        "language" : "pt_PT"
      },
      {
        "target" : "Pada jarak minimum sekarang. Tidak boleh dilaraskan lebih rendah.",
        "filename" : "Accessibility.strings",
        "language" : "ms"
      },
      {
        "target" : "Vid minsta avstånd just nu. Kan inte justera lägre.",
        "filename" : "Accessibility.strings",
        "language" : "sv"
      },
      {
        "target" : "Jste na minimální vzdálenosti. Víc už přiblížit nelze.",
        "filename" : "Accessibility.strings",
        "language" : "cs"
      },
      {
        "target" : "현재 거리가 최소 상태이며, 더 낮게 조절할 수 없습니다.",
        "filename" : "Accessibility.strings",
        "language" : "ko"
      },
      {
        "target" : "Minimum distanse er nådd. Kan ikke justere lavere.",
        "filename" : "Accessibility.strings",
        "language" : "no"
      },
      {
        "target" : "Jelenleg a minimális távolság van beállítva. Nem állítható alacsonyabb értékre.",
        "filename" : "Accessibility.strings",
        "language" : "hu"
      },
      {
        "target" : "目前位於最近距離。無法再調整更少。",
        "filename" : "Accessibility.strings",
        "language" : "zh_HK"
      },
      {
        "target" : "Şu anda minimum mesafede. Daha alçağa ayarlanamıyor.",
        "filename" : "Accessibility.strings",
        "language" : "tr"
      },
      {
        "target" : "Odległość jest już minimalna. Nie można jej zmniejszyć.",
        "filename" : "Accessibility.strings",
        "language" : "pl"
      },
      {
        "target" : "目前位於最近距離。無法再調整更少。",
        "filename" : "Accessibility.strings",
        "language" : "zh_TW"
      },
      {
        "target" : "Currently at minimum distance. Cannot adjust any lower.",
        "filename" : "Accessibility.strings",
        "language" : "en_GB"
      },
      {
        "target" : "Hiện đang ở khoảng cách tối thiểu. Không thể điều chỉnh thấp hơn.",
        "filename" : "Accessibility.strings",
        "language" : "vi"
      },
      {
        "target" : "Минимальное расстояние. Перемещение ближе невозможно.",
        "filename" : "Accessibility.strings",
        "language" : "ru"
      },
      {
        "target" : "Distance minimale atteinte. Impossible de la diminuer davantage.",
        "filename" : "Accessibility.strings",
        "language" : "fr_CA"
      },
      {
        "target" : "Distance minimale atteinte. Impossible de placer l’objet plus près.",
        "filename" : "Accessibility.strings",
        "language" : "fr"
      },
      {
        "target" : "Tällä hetkellä vähimmäisetäisyydellä. Ei voida säätää alhaisemmaksi.",
        "filename" : "Accessibility.strings",
        "language" : "fi"
      },
      {
        "target" : "Jarak saat ini sudah minimal. Tidak dapat disesuaikan lebih rendah.",
        "filename" : "Accessibility.strings",
        "language" : "id"
      },
      {
        "target" : "Momenteel op minimale afstand. Kan niet verder worden aangepast.",
        "filename" : "Accessibility.strings",
        "language" : "nl"
      },
      {
        "target" : "อยู่ในระยะใกล้สุดแล้ว ไม่สามารถปรับได้น้อยกว่านี้",
        "filename" : "Accessibility.strings",
        "language" : "th"
      },
      {
        "target" : "Atualmente na distância mínima. Não é possível ajustar abaixo.",
        "filename" : "Accessibility.strings",
        "language" : "pt"
      },
      {
        "target" : "A fost atinsă distanța minimă. Nu se poate ajusta mai jos.",
        "filename" : "Accessibility.strings",
        "language" : "ro"
      },
      {
        "target" : "Trenutačno na minimalnoj udaljenosti. Ne može se podesiti na niže.",
        "filename" : "Accessibility.strings",
        "language" : "hr"
      },
      {
        "target" : "वर्तमान में न्यूनतम दूरी पर। इससे कम पर ऐडजस्ट नहीं किया जा सकता है।",
        "filename" : "Accessibility.strings",
        "language" : "hi"
      },
      {
        "target" : "S’ha ajustat a la distància mínima. Ja no es pot ajustar més.",
        "filename" : "Accessibility.strings",
        "language" : "ca"
      }
    ],
    "distance.in.feet" : [
      {
        "target" : "%lu Fuß",
        "filename" : "Accessibility.strings",
        "language" : "de"
      },
      {
        "target" : "%lu רגל",
        "filename" : "Accessibility.strings",
        "language" : "he"
      },
      {
        "target" : "%lu feet",
        "filename" : "Accessibility.strings",
        "language" : "en_AU"
      },
      {
        "target" : "‏%lu قدم",
        "filename" : "Accessibility.strings",
        "language" : "ar"
      },
      {
        "target" : "%lu πόδια",
        "filename" : "Accessibility.strings",
        "language" : "el"
      },
      {
        "target" : "%luフィート",
        "filename" : "Accessibility.strings",
        "language" : "ja"
      },
      {
        "target" : "%lu feet",
        "filename" : "Accessibility.strings",
        "language" : "en"
      },
      {
        "target" : "Футів: %lu",
        "filename" : "Accessibility.strings",
        "language" : "uk"
      },
      {
        "target" : "%lu pies",
        "filename" : "Accessibility.strings",
        "language" : "es_419"
      },
      {
        "target" : "%lu英尺",
        "filename" : "Accessibility.strings",
        "language" : "zh_CN"
      },
      {
        "target" : "%lu pies",
        "filename" : "Accessibility.strings",
        "language" : "es"
      },
      {
        "target" : "%lu fod",
        "filename" : "Accessibility.strings",
        "language" : "da"
      },
      {
        "target" : "%lu piedi",
        "filename" : "Accessibility.strings",
        "language" : "it"
      },
      {
        "target" : "Stopy: %lu",
        "filename" : "Accessibility.strings",
        "language" : "sk"
      },
      {
        "target" : "%lu pés",
        "filename" : "Accessibility.strings",
        "language" : "pt_PT"
      },
      {
        "target" : "%lu kaki",
        "filename" : "Accessibility.strings",
        "language" : "ms"
      },
      {
        "target" : "%lu fot",
        "filename" : "Accessibility.strings",
        "language" : "sv"
      },
      {
        "target" : "%lu ft",
        "filename" : "Accessibility.strings",
        "language" : "cs"
      },
      {
        "target" : "%lu피트",
        "filename" : "Accessibility.strings",
        "language" : "ko"
      },
      {
        "target" : "%lu fot",
        "filename" : "Accessibility.strings",
        "language" : "no"
      },
      {
        "target" : "%lu láb",
        "filename" : "Accessibility.strings",
        "language" : "hu"
      },
      {
        "target" : "%lu呎",
        "filename" : "Accessibility.strings",
        "language" : "zh_HK"
      },
      {
        "target" : "%lu fit",
        "filename" : "Accessibility.strings",
        "language" : "tr"
      },
      {
        "target" : "Stóp: %lu",
        "filename" : "Accessibility.strings",
        "language" : "pl"
      },
      {
        "target" : "%lu英尺",
        "filename" : "Accessibility.strings",
        "language" : "zh_TW"
      },
      {
        "target" : "%lu feet",
        "filename" : "Accessibility.strings",
        "language" : "en_GB"
      },
      {
        "target" : "%lu feet",
        "filename" : "Accessibility.strings",
        "language" : "vi"
      },
      {
        "target" : "Футов: %lu",
        "filename" : "Accessibility.strings",
        "language" : "ru"
      },
      {
        "target" : "%lu pieds",
        "filename" : "Accessibility.strings",
        "language" : "fr_CA"
      },
      {
        "target" : "%lu pieds",
        "filename" : "Accessibility.strings",
        "language" : "fr"
      },
      {
        "target" : "%lu jalkaa",
        "filename" : "Accessibility.strings",
        "language" : "fi"
      },
      {
        "target" : "%lu kaki",
        "filename" : "Accessibility.strings",
        "language" : "id"
      },
      {
        "target" : "%lu voet",
        "filename" : "Accessibility.strings",
        "language" : "nl"
      },
      {
        "target" : "%lu ฟุต",
        "filename" : "Accessibility.strings",
        "language" : "th"
      },
      {
        "target" : "%lu pés",
        "filename" : "Accessibility.strings",
        "language" : "pt"
      },
      {
        "target" : "%lu picioare",
        "filename" : "Accessibility.strings",
        "language" : "ro"
      },
      {
        "target" : "stopa: %lu",
        "filename" : "Accessibility.strings",
        "language" : "hr"
      },
      {
        "target" : "%lu फ़ुट",
        "filename" : "Accessibility.strings",
        "language" : "hi"
      },
      {
        "target" : "%lu peus",
        "filename" : "Accessibility.strings",
        "language" : "ca"
      }
    ],
    "add.item.to.iPhone" : [
      {
        "target" : "Animation eines iPhone, das zum Koppeln näher an ein AirTag bewegt wird",
        "filename" : "Accessibility-B389.strings",
        "language" : "de"
      },
      {
        "target" : "הנפשה של הזזת iPhone קרוב יותר אל AirTag על-מנת להתחיל בקישור",
        "filename" : "Accessibility-B389.strings",
        "language" : "he"
      },
      {
        "target" : "Animation of moving an iPhone closer to an AirTag to begin pairing",
        "filename" : "Accessibility-B389.strings",
        "language" : "en_AU"
      },
      {
        "target" : "رسم متحرك لـ iPhone يتحرك مقتربًا من AirTag لبدء الاقتران",
        "filename" : "Accessibility-B389.strings",
        "language" : "ar"
      },
      {
        "target" : "Κινούμενη εικόνα ενός iPhone που μετακινείται κοντά σε ένα AirTag για έναρξη ζευγοποίησης",
        "filename" : "Accessibility-B389.strings",
        "language" : "el"
      },
      {
        "target" : "iPhoneをAirTagに近づけてペアリングを始めるアニメーション",
        "filename" : "Accessibility-B389.strings",
        "language" : "ja"
      },
      {
        "target" : "Animation of moving an iPhone closer to an AirTag to begin pairing",
        "filename" : "Accessibility-B389.strings",
        "language" : "en"
      },
      {
        "target" : "Анімація iPhone, що наближається до тега AirTag для створення пари",
        "filename" : "Accessibility-B389.strings",
        "language" : "uk"
      },
      {
        "target" : "Animación de un iPhone que se acerca a un AirTag para iniciar el enlace",
        "filename" : "Accessibility-B389.strings",
        "language" : "es_419"
      },
      {
        "target" : "将iPhone靠近AirTag以开始配对的动画",
        "filename" : "Accessibility-B389.strings",
        "language" : "zh_CN"
      },
      {
        "target" : "Animación de un iPhone acercándose a un AirTag para iniciar el enlace",
        "filename" : "Accessibility-B389.strings",
        "language" : "es"
      },
      {
        "target" : "Animation af en iPhone, der kommer tættere på et AirTag for at etablere pardannelse",
        "filename" : "Accessibility-B389.strings",
        "language" : "da"
      },
      {
        "target" : "Animazione di un iPhone che si avvicina a un AirTag per iniziare l'abbinamento",
        "filename" : "Accessibility-B389.strings",
        "language" : "it"
      },
      {
        "target" : "Animácia iPhonu, ktorý sa približuje k AirTagu, aby sa spustilo párovanie",
        "filename" : "Accessibility-B389.strings",
        "language" : "sk"
      },
      {
        "target" : "Animação de um iPhone a ser aproximado de um AirTag para começar o emparelhamento",
        "filename" : "Accessibility-B389.strings",
        "language" : "pt_PT"
      },
      {
        "target" : "Animasi menggerakkan iPhone lebih dekat dengan AirTag untuk memulakan berpasangan",
        "filename" : "Accessibility-B389.strings",
        "language" : "ms"
      },
      {
        "target" : "Animering av en iPhone som flyttas närmare en AirTag så att parkopplingen kan börja",
        "filename" : "Accessibility-B389.strings",
        "language" : "sv"
      },
      {
        "target" : "Animace přiblížení iPhonu k AirTagu a zahájení párování",
        "filename" : "Accessibility-B389.strings",
        "language" : "cs"
      },
      {
        "target" : "페어링을 시작하기 위해 iPhone을 AirTag 가까이 이동하는 영상",
        "filename" : "Accessibility-B389.strings",
        "language" : "ko"
      },
      {
        "target" : "Animasjon av en iPhone som flyttes nærmere en AirTag for å starte sammenkobling",
        "filename" : "Accessibility-B389.strings",
        "language" : "no"
      },
      {
        "target" : "Animáció, amelyen egy iPhone egy AirTag közelébe van helyezve a párosítás megkezdéséhez",
        "filename" : "Accessibility-B389.strings",
        "language" : "hu"
      },
      {
        "target" : "將iPhone靠近AirTag以開始配對的動畫",
        "filename" : "Accessibility-B389.strings",
        "language" : "zh_HK"
      },
      {
        "target" : "Eşlemeyi başlatmak için bir iPhone’un AirTag’e yaklaştırılmasını gösteren canlandırma",
        "filename" : "Accessibility-B389.strings",
        "language" : "tr"
      },
      {
        "target" : "Animacja przedstawiająca iPhone’a zbliżanego do AirTaga w celu połączenia ich w parę",
        "filename" : "Accessibility-B389.strings",
        "language" : "pl"
      },
      {
        "target" : "將iPhone靠近AirTag以開始配對的動畫",
        "filename" : "Accessibility-B389.strings",
        "language" : "zh_TW"
      },
      {
        "target" : "Animation of moving an iPhone closer to an AirTag to begin pairing",
        "filename" : "Accessibility-B389.strings",
        "language" : "en_GB"
      },
      {
        "target" : "Hình động minh họa việc di chuyển iPhone đến gần AirTag hơn để bắt đầu ghép đôi",
        "filename" : "Accessibility-B389.strings",
        "language" : "vi"
      },
      {
        "target" : "Анимация, показывающая, как iPhone подносят к AirTag, чтобы начать создание пары",
        "filename" : "Accessibility-B389.strings",
        "language" : "ru"
      },
      {
        "target" : "Animation du déplacement d’un iPhone vers un AirTag pour commencer le jumelage",
        "filename" : "Accessibility-B389.strings",
        "language" : "fr_CA"
      },
      {
        "target" : "Animation d’un iPhone approchant d’un AirTag pour commencer le jumelage",
        "filename" : "Accessibility-B389.strings",
        "language" : "fr"
      },
      {
        "target" : "Animaatio iPhonesta, jota siirretään lähemmäs AirTagia parin muodostamista varten",
        "filename" : "Accessibility-B389.strings",
        "language" : "fi"
      },
      {
        "target" : "Animasi mendekatkan iPhone ke AirTag untuk memulai pemasangan",
        "filename" : "Accessibility-B389.strings",
        "language" : "id"
      },
      {
        "target" : "Animatie van een iPhone die dichter bij een AirTag wordt gehouden om te beginnen met koppelen.",
        "filename" : "Accessibility-B389.strings",
        "language" : "nl"
      },
      {
        "target" : "ภาพเคลื่อนไหวของ iPhone เคลื่อนเข้าใกล้ AirTag เพื่อเริ่มจับคู่",
        "filename" : "Accessibility-B389.strings",
        "language" : "th"
      },
      {
        "target" : "Animação de um iPhone sendo aproximado de um AirTag para iniciar o emparelhamento",
        "filename" : "Accessibility-B389.strings",
        "language" : "pt"
      },
      {
        "target" : "Animația apropierii unui iPhone de un AirTag pentru începerea asocierii",
        "filename" : "Accessibility-B389.strings",
        "language" : "ro"
      },
      {
        "target" : "Animacija približavanja iPhonea AirTagu radi pokretanja uparivanja",
        "filename" : "Accessibility-B389.strings",
        "language" : "hr"
      },
      {
        "target" : "पेयरिंग शुरू करने के लिए iPhone को AirTag के नज़दीक ले जाने का ऐनिमेशन",
        "filename" : "Accessibility-B389.strings",
        "language" : "hi"
      },
      {
        "target" : "Animació en què s’apropa un iPhone a un AirTag per enllaçar‑los",
        "filename" : "Accessibility-B389.strings",
        "language" : "ca"
      }
    ],
    "distance.in.meter" : [
      {
        "target" : "%lu Meter",
        "filename" : "Accessibility.strings",
        "language" : "de"
      },
      {
        "target" : "%lu מטר",
        "filename" : "Accessibility.strings",
        "language" : "he"
      },
      {
        "target" : "%lu metres",
        "filename" : "Accessibility.strings",
        "language" : "en_AU"
      },
      {
        "target" : "%lu متر",
        "filename" : "Accessibility.strings",
        "language" : "ar"
      },
      {
        "target" : "%lu μέτρα",
        "filename" : "Accessibility.strings",
        "language" : "el"
      },
      {
        "target" : "%luメートル",
        "filename" : "Accessibility.strings",
        "language" : "ja"
      },
      {
        "target" : "%lu meters",
        "filename" : "Accessibility.strings",
        "language" : "en"
      },
      {
        "target" : "Метрів: %lu",
        "filename" : "Accessibility.strings",
        "language" : "uk"
      },
      {
        "target" : "%lu metros",
        "filename" : "Accessibility.strings",
        "language" : "es_419"
      },
      {
        "target" : "%lu米",
        "filename" : "Accessibility.strings",
        "language" : "zh_CN"
      },
      {
        "target" : "%lu metros",
        "filename" : "Accessibility.strings",
        "language" : "es"
      },
      {
        "target" : "%lu meter",
        "filename" : "Accessibility.strings",
        "language" : "da"
      },
      {
        "target" : "%lu metri",
        "filename" : "Accessibility.strings",
        "language" : "it"
      },
      {
        "target" : "Metre: %lu",
        "filename" : "Accessibility.strings",
        "language" : "sk"
      },
      {
        "target" : "%lu metros",
        "filename" : "Accessibility.strings",
        "language" : "pt_PT"
      },
      {
        "target" : "%lu meter",
        "filename" : "Accessibility.strings",
        "language" : "ms"
      },
      {
        "target" : "%lu meter",
        "filename" : "Accessibility.strings",
        "language" : "sv"
      },
      {
        "target" : "%lu m",
        "filename" : "Accessibility.strings",
        "language" : "cs"
      },
      {
        "target" : "%lu미터",
        "filename" : "Accessibility.strings",
        "language" : "ko"
      },
      {
        "target" : "%lu meter",
        "filename" : "Accessibility.strings",
        "language" : "no"
      },
      {
        "target" : "%lu méter",
        "filename" : "Accessibility.strings",
        "language" : "hu"
      },
      {
        "target" : "%lu米",
        "filename" : "Accessibility.strings",
        "language" : "zh_HK"
      },
      {
        "target" : "%lu metre",
        "filename" : "Accessibility.strings",
        "language" : "tr"
      },
      {
        "target" : "Metrów: %lu",
        "filename" : "Accessibility.strings",
        "language" : "pl"
      },
      {
        "target" : "%lu公尺",
        "filename" : "Accessibility.strings",
        "language" : "zh_TW"
      },
      {
        "target" : "%lu metres",
        "filename" : "Accessibility.strings",
        "language" : "en_GB"
      },
      {
        "target" : "%lu mét",
        "filename" : "Accessibility.strings",
        "language" : "vi"
      },
      {
        "target" : "Метров: %lu",
        "filename" : "Accessibility.strings",
        "language" : "ru"
      },
      {
        "target" : "%lu mètres",
        "filename" : "Accessibility.strings",
        "language" : "fr_CA"
      },
      {
        "target" : "%lu mètres",
        "filename" : "Accessibility.strings",
        "language" : "fr"
      },
      {
        "target" : "%lu metriä",
        "filename" : "Accessibility.strings",
        "language" : "fi"
      },
      {
        "target" : "%lu meter",
        "filename" : "Accessibility.strings",
        "language" : "id"
      },
      {
        "target" : "%lu meter",
        "filename" : "Accessibility.strings",
        "language" : "nl"
      },
      {
        "target" : "%lu เมตร",
        "filename" : "Accessibility.strings",
        "language" : "th"
      },
      {
        "target" : "%lu metros",
        "filename" : "Accessibility.strings",
        "language" : "pt"
      },
      {
        "target" : "%lu metri",
        "filename" : "Accessibility.strings",
        "language" : "ro"
      },
      {
        "target" : "metara: %lu",
        "filename" : "Accessibility.strings",
        "language" : "hr"
      },
      {
        "target" : "%lu मीटर",
        "filename" : "Accessibility.strings",
        "language" : "hi"
      },
      {
        "target" : "%lu metres",
        "filename" : "Accessibility.strings",
        "language" : "ca"
      }
    ],
    "add.item.to.iPad" : [
      {
        "target" : "Animation eines iPad, das zum Koppeln näher an ein AirTag bewegt wird",
        "filename" : "Accessibility-B389.strings",
        "language" : "de"
      },
      {
        "target" : "הנפשה של הזזת iPad קרוב יותר אל AirTag על-מנת להתחיל בקישור",
        "filename" : "Accessibility-B389.strings",
        "language" : "he"
      },
      {
        "target" : "Animation of moving an iPad closer to an AirTag to begin pairing",
        "filename" : "Accessibility-B389.strings",
        "language" : "en_AU"
      },
      {
        "target" : "رسم متحرك لـ iPad يتحرك مقتربًا من AirTag لبدء الاقتران",
        "filename" : "Accessibility-B389.strings",
        "language" : "ar"
      },
      {
        "target" : "Κινούμενη εικόνα ενός iPad που μετακινείται κοντά σε ένα AirTag για έναρξη ζευγοποίησης",
        "filename" : "Accessibility-B389.strings",
        "language" : "el"
      },
      {
        "target" : "iPadをAirTagに近づけてペアリングを始めるアニメーション",
        "filename" : "Accessibility-B389.strings",
        "language" : "ja"
      },
      {
        "target" : "Animation of moving an iPad closer to an AirTag to begin pairing",
        "filename" : "Accessibility-B389.strings",
        "language" : "en"
      },
      {
        "target" : "Анімація iPad, що наближається до тега AirTag для створення пари",
        "filename" : "Accessibility-B389.strings",
        "language" : "uk"
      },
      {
        "target" : "Animación de un iPad que se acerca a un AirTag para iniciar el enlace",
        "filename" : "Accessibility-B389.strings",
        "language" : "es_419"
      },
      {
        "target" : "将iPad靠近AirTag以开始配对的动画",
        "filename" : "Accessibility-B389.strings",
        "language" : "zh_CN"
      },
      {
        "target" : "Animación de un iPad acercándose a un AirTag para iniciar el enlace",
        "filename" : "Accessibility-B389.strings",
        "language" : "es"
      },
      {
        "target" : "Animation af en iPad, der kommer tættere på et AirTag for at etablere pardannelse",
        "filename" : "Accessibility-B389.strings",
        "language" : "da"
      },
      {
        "target" : "Animazione di un iPad che si avvicina a un AirTag per iniziare l'abbinamento",
        "filename" : "Accessibility-B389.strings",
        "language" : "it"
      },
      {
        "target" : "Animácia iPadu, ktorý sa približuje k AirTagu, aby sa spustilo párovanie",
        "filename" : "Accessibility-B389.strings",
        "language" : "sk"
      },
      {
        "target" : "Animação de um iPad a ser aproximado de um AirTag para começar o emparelhamento",
        "filename" : "Accessibility-B389.strings",
        "language" : "pt_PT"
      },
      {
        "target" : "Animasi menggerakkan iPad lebih dekat dengan AirTag untuk memulakan berpasangan",
        "filename" : "Accessibility-B389.strings",
        "language" : "ms"
      },
      {
        "target" : "Animering av en iPad som flyttas närmare en AirTag så att parkopplingen kan börja",
        "filename" : "Accessibility-B389.strings",
        "language" : "sv"
      },
      {
        "target" : "Animace přiblížení iPadu k AirTagu a zahájení párování",
        "filename" : "Accessibility-B389.strings",
        "language" : "cs"
      },
      {
        "target" : "페어링을 시작하기 위해 iPad를 AirTag 가까이 이동하는 영상",
        "filename" : "Accessibility-B389.strings",
        "language" : "ko"
      },
      {
        "target" : "Animasjon av en iPad som flyttes nærmere en AirTag for å starte sammenkobling",
        "filename" : "Accessibility-B389.strings",
        "language" : "no"
      },
      {
        "target" : "Animáció, amelyen egy iPad egy AirTaghez van közelítve a párosítás megkezdéséhez",
        "filename" : "Accessibility-B389.strings",
        "language" : "hu"
      },
      {
        "target" : "將iPad靠近AirTag以開始配對的動畫",
        "filename" : "Accessibility-B389.strings",
        "language" : "zh_HK"
      },
      {
        "target" : "Eşlemeyi başlatmak için bir iPad’in AirTag’e yaklaştırılmasını gösteren canlandırma",
        "filename" : "Accessibility-B389.strings",
        "language" : "tr"
      },
      {
        "target" : "Animacja przedstawiająca iPada zbliżanego do AirTaga w celu połączenia ich w parę",
        "filename" : "Accessibility-B389.strings",
        "language" : "pl"
      },
      {
        "target" : "將iPad靠近AirTag以開始配對的動畫",
        "filename" : "Accessibility-B389.strings",
        "language" : "zh_TW"
      },
      {
        "target" : "Animation of moving an iPad closer to an AirTag to begin pairing",
        "filename" : "Accessibility-B389.strings",
        "language" : "en_GB"
      },
      {
        "target" : "Hình động minh họa việc di chuyển iPad đến gần AirTag hơn để bắt đầu ghép đôi",
        "filename" : "Accessibility-B389.strings",
        "language" : "vi"
      },
      {
        "target" : "Анимация, показывающая, как iPad подносят к AirTag, чтобы начать создание пары",
        "filename" : "Accessibility-B389.strings",
        "language" : "ru"
      },
      {
        "target" : "Animation du déplacement d’un iPad vers un AirTag pour commencer le jumelage",
        "filename" : "Accessibility-B389.strings",
        "language" : "fr_CA"
      },
      {
        "target" : "Animation d’un iPad approchant d’un AirTag pour commencer le jumelage",
        "filename" : "Accessibility-B389.strings",
        "language" : "fr"
      },
      {
        "target" : "Animaatio iPadista, jota siirretään lähemmäs AirTagia parin muodostamista varten",
        "filename" : "Accessibility-B389.strings",
        "language" : "fi"
      },
      {
        "target" : "Animasi mendekatkan iPad ke AirTag untuk memulai pemasangan",
        "filename" : "Accessibility-B389.strings",
        "language" : "id"
      },
      {
        "target" : "Animatie van een iPad die dichter bij een AirTag wordt gehouden om te beginnen met koppelen",
        "filename" : "Accessibility-B389.strings",
        "language" : "nl"
      },
      {
        "target" : "ภาพเคลื่อนไหวของ iPad เคลื่อนเข้าใกล้ AirTag เพื่อเริ่มจับคู่",
        "filename" : "Accessibility-B389.strings",
        "language" : "th"
      },
      {
        "target" : "Animação de um iPad sendo aproximado de um AirTag para iniciar o emparelhamento",
        "filename" : "Accessibility-B389.strings",
        "language" : "pt"
      },
      {
        "target" : "Animația apropierii unui iPad de un AirTag pentru începerea asocierii",
        "filename" : "Accessibility-B389.strings",
        "language" : "ro"
      },
      {
        "target" : "Animacija približavanja iPada AirTagu radi pokretanja uparivanja",
        "filename" : "Accessibility-B389.strings",
        "language" : "hr"
      },
      {
        "target" : "पेयरिंग शुरू करने के लिए iPad को AirTag के नज़दीक ले जाने का ऐनिमेशन",
        "filename" : "Accessibility-B389.strings",
        "language" : "hi"
      },
      {
        "target" : "Animació en què s’apropa un iPad a un AirTag per enllaçar‑los",
        "filename" : "Accessibility-B389.strings",
        "language" : "ca"
      }
    ],
    "item.compass" : [
      {
        "target" : "Kompass",
        "filename" : "Accessibility-B389.strings",
        "language" : "de"
      },
      {
        "target" : "מצפן",
        "filename" : "Accessibility-B389.strings",
        "language" : "he"
      },
      {
        "target" : "Compass",
        "filename" : "Accessibility-B389.strings",
        "language" : "en_AU"
      },
      {
        "target" : "البوصلة",
        "filename" : "Accessibility-B389.strings",
        "language" : "ar"
      },
      {
        "target" : "Πυξίδα",
        "filename" : "Accessibility-B389.strings",
        "language" : "el"
      },
      {
        "target" : "コンパス",
        "filename" : "Accessibility-B389.strings",
        "language" : "ja"
      },
      {
        "target" : "Compass",
        "filename" : "Accessibility-B389.strings",
        "language" : "en"
      },
      {
        "target" : "Компас",
        "filename" : "Accessibility-B389.strings",
        "language" : "uk"
      },
      {
        "target" : "Brújula",
        "filename" : "Accessibility-B389.strings",
        "language" : "es_419"
      },
      {
        "target" : "指南针",
        "filename" : "Accessibility-B389.strings",
        "language" : "zh_CN"
      },
      {
        "target" : "Brújula",
        "filename" : "Accessibility-B389.strings",
        "language" : "es"
      },
      {
        "target" : "Kompas",
        "filename" : "Accessibility-B389.strings",
        "language" : "da"
      },
      {
        "target" : "Bussola",
        "filename" : "Accessibility-B389.strings",
        "language" : "it"
      },
      {
        "target" : "Kompas",
        "filename" : "Accessibility-B389.strings",
        "language" : "sk"
      },
      {
        "target" : "Bússola",
        "filename" : "Accessibility-B389.strings",
        "language" : "pt_PT"
      },
      {
        "target" : "Kompas",
        "filename" : "Accessibility-B389.strings",
        "language" : "ms"
      },
      {
        "target" : "Kompass",
        "filename" : "Accessibility-B389.strings",
        "language" : "sv"
      },
      {
        "target" : "Kompas",
        "filename" : "Accessibility-B389.strings",
        "language" : "cs"
      },
      {
        "target" : "나침반",
        "filename" : "Accessibility-B389.strings",
        "language" : "ko"
      },
      {
        "target" : "Kompass",
        "filename" : "Accessibility-B389.strings",
        "language" : "no"
      },
      {
        "target" : "Iránytű",
        "filename" : "Accessibility-B389.strings",
        "language" : "hu"
      },
      {
        "target" : "指南針",
        "filename" : "Accessibility-B389.strings",
        "language" : "zh_HK"
      },
      {
        "target" : "Pusula",
        "filename" : "Accessibility-B389.strings",
        "language" : "tr"
      },
      {
        "target" : "Kompas",
        "filename" : "Accessibility-B389.strings",
        "language" : "pl"
      },
      {
        "target" : "指南針",
        "filename" : "Accessibility-B389.strings",
        "language" : "zh_TW"
      },
      {
        "target" : "Compass",
        "filename" : "Accessibility-B389.strings",
        "language" : "en_GB"
      },
      {
        "target" : "La bàn",
        "filename" : "Accessibility-B389.strings",
        "language" : "vi"
      },
      {
        "target" : "Компас",
        "filename" : "Accessibility-B389.strings",
        "language" : "ru"
      },
      {
        "target" : "Boussole",
        "filename" : "Accessibility-B389.strings",
        "language" : "fr_CA"
      },
      {
        "target" : "Boussole",
        "filename" : "Accessibility-B389.strings",
        "language" : "fr"
      },
      {
        "target" : "Kompassi",
        "filename" : "Accessibility-B389.strings",
        "language" : "fi"
      },
      {
        "target" : "Kompas",
        "filename" : "Accessibility-B389.strings",
        "language" : "id"
      },
      {
        "target" : "Kompas",
        "filename" : "Accessibility-B389.strings",
        "language" : "nl"
      },
      {
        "target" : "เข็มทิศ",
        "filename" : "Accessibility-B389.strings",
        "language" : "th"
      },
      {
        "target" : "Bússola",
        "filename" : "Accessibility-B389.strings",
        "language" : "pt"
      },
      {
        "target" : "Busolă",
        "filename" : "Accessibility-B389.strings",
        "language" : "ro"
      },
      {
        "target" : "Kompas",
        "filename" : "Accessibility-B389.strings",
        "language" : "hr"
      },
      {
        "target" : "दिशासूचक",
        "filename" : "Accessibility-B389.strings",
        "language" : "hi"
      },
      {
        "target" : "Brúixola",
        "filename" : "Accessibility-B389.strings",
        "language" : "ca"
      }
    ],
    "location.range.handle" : [
      {
        "target" : "Standortbereichsregler",
        "filename" : "Accessibility.strings",
        "language" : "de"
      },
      {
        "target" : "ידית של טווח מיקום",
        "filename" : "Accessibility.strings",
        "language" : "he"
      },
      {
        "target" : "Location Range Handle",
        "filename" : "Accessibility.strings",
        "language" : "en_AU"
      },
      {
        "target" : "مؤشر نطاق الموقع",
        "filename" : "Accessibility.strings",
        "language" : "ar"
      },
      {
        "target" : "Λαβή εύρους τοποθεσίας",
        "filename" : "Accessibility.strings",
        "language" : "el"
      },
      {
        "target" : "位置情報範囲ハンドル",
        "filename" : "Accessibility.strings",
        "language" : "ja"
      },
      {
        "target" : "Location Range Handle",
        "filename" : "Accessibility.strings",
        "language" : "en"
      },
      {
        "target" : "Засіб змінення радіусу пошуку",
        "filename" : "Accessibility.strings",
        "language" : "uk"
      },
      {
        "target" : "Asa de rango de ubicación",
        "filename" : "Accessibility.strings",
        "language" : "es_419"
      },
      {
        "target" : "位置范围控制柄",
        "filename" : "Accessibility.strings",
        "language" : "zh_CN"
      },
      {
        "target" : "Tirador del intervalo de ubicación",
        "filename" : "Accessibility.strings",
        "language" : "es"
      },
      {
        "target" : "Håndtag til lokalitetsudsnit",
        "filename" : "Accessibility.strings",
        "language" : "da"
      },
      {
        "target" : "Maniglia area posizione",
        "filename" : "Accessibility.strings",
        "language" : "it"
      },
      {
        "target" : "Úchyt rozsahu oblasti",
        "filename" : "Accessibility.strings",
        "language" : "sk"
      },
      {
        "target" : "Manípulo de alcance da localização",
        "filename" : "Accessibility.strings",
        "language" : "pt_PT"
      },
      {
        "target" : "Pemegang Julat Lokasi",
        "filename" : "Accessibility.strings",
        "language" : "ms"
      },
      {
        "target" : "Platsomfångshandtag",
        "filename" : "Accessibility.strings",
        "language" : "sv"
      },
      {
        "target" : "Úchyt rozsahu polohy",
        "filename" : "Accessibility.strings",
        "language" : "cs"
      },
      {
        "target" : "위치 범위 핸들",
        "filename" : "Accessibility.strings",
        "language" : "ko"
      },
      {
        "target" : "Posisjonsavgrensningshåndtak",
        "filename" : "Accessibility.strings",
        "language" : "no"
      },
      {
        "target" : "Helytartomány kezelője",
        "filename" : "Accessibility.strings",
        "language" : "hu"
      },
      {
        "target" : "位置範圍控點",
        "filename" : "Accessibility.strings",
        "language" : "zh_HK"
      },
      {
        "target" : "Konum Aralığı Tutamağı",
        "filename" : "Accessibility.strings",
        "language" : "tr"
      },
      {
        "target" : "Uchwyt zasięgu dla miejsca",
        "filename" : "Accessibility.strings",
        "language" : "pl"
      },
      {
        "target" : "位置範圍控點",
        "filename" : "Accessibility.strings",
        "language" : "zh_TW"
      },
      {
        "target" : "Location Range Handle",
        "filename" : "Accessibility.strings",
        "language" : "en_GB"
      },
      {
        "target" : "Điều khiển phạm vi vị trí",
        "filename" : "Accessibility.strings",
        "language" : "vi"
      },
      {
        "target" : "Манипулятор выбора диапазона геопозиции",
        "filename" : "Accessibility.strings",
        "language" : "ru"
      },
      {
        "target" : "Poignée de périmètre",
        "filename" : "Accessibility.strings",
        "language" : "fr_CA"
      },
      {
        "target" : "Poignée de plage de positionnement",
        "filename" : "Accessibility.strings",
        "language" : "fr"
      },
      {
        "target" : "Sijaintialueen kahva",
        "filename" : "Accessibility.strings",
        "language" : "fi"
      },
      {
        "target" : "Pengendali Cakupan Lokasi",
        "filename" : "Accessibility.strings",
        "language" : "id"
      },
      {
        "target" : "Handgreep locatiebereik",
        "filename" : "Accessibility.strings",
        "language" : "nl"
      },
      {
        "target" : "ขอบจับระยะตำแหน่งที่ตั้ง",
        "filename" : "Accessibility.strings",
        "language" : "th"
      },
      {
        "target" : "Puxador de Alcance de Localização",
        "filename" : "Accessibility.strings",
        "language" : "pt"
      },
      {
        "target" : "Control interval localizare",
        "filename" : "Accessibility.strings",
        "language" : "ro"
      },
      {
        "target" : "Hvatište raspona lokacije",
        "filename" : "Accessibility.strings",
        "language" : "hr"
      },
      {
        "target" : "स्थान रेंज हैंडल",
        "filename" : "Accessibility.strings",
        "language" : "hi"
      },
      {
        "target" : "Marcador dels límits de la ubicació",
        "filename" : "Accessibility.strings",
        "language" : "ca"
      }
    ],
    "item.within.in.reach.mode" : [
      {
        "target" : "Objekt in Reichweite",
        "filename" : "Accessibility-B389.strings",
        "language" : "de"
      },
      {
        "target" : "הפריט בהישג יד",
        "filename" : "Accessibility-B389.strings",
        "language" : "he"
      },
      {
        "target" : "Item within reach",
        "filename" : "Accessibility-B389.strings",
        "language" : "en_AU"
      },
      {
        "target" : "عنصر في المتناول",
        "filename" : "Accessibility-B389.strings",
        "language" : "ar"
      },
      {
        "target" : "Αντικείμενο σε απόσταση αγγίγματος",
        "filename" : "Accessibility-B389.strings",
        "language" : "el"
      },
      {
        "target" : "持ち物は手の届く範囲にあります",
        "filename" : "Accessibility-B389.strings",
        "language" : "ja"
      },
      {
        "target" : "Item within reach",
        "filename" : "Accessibility-B389.strings",
        "language" : "en"
      },
      {
        "target" : "Обʼєкт у зоні досяжності",
        "filename" : "Accessibility-B389.strings",
        "language" : "uk"
      },
      {
        "target" : "Artículo al alcance",
        "filename" : "Accessibility-B389.strings",
        "language" : "es_419"
      },
      {
        "target" : "伸手可及的物品",
        "filename" : "Accessibility-B389.strings",
        "language" : "zh_CN"
      },
      {
        "target" : "Objeto al alcance",
        "filename" : "Accessibility-B389.strings",
        "language" : "es"
      },
      {
        "target" : "Genstand indenfor rækkevidde",
        "filename" : "Accessibility-B389.strings",
        "language" : "da"
      },
      {
        "target" : "Oggetto a portata di mano",
        "filename" : "Accessibility-B389.strings",
        "language" : "it"
      },
      {
        "target" : "Predmet v dosahu",
        "filename" : "Accessibility-B389.strings",
        "language" : "sk"
      },
      {
        "target" : "Objeto ao alcance",
        "filename" : "Accessibility-B389.strings",
        "language" : "pt_PT"
      },
      {
        "target" : "Item dalam jangkauan",
        "filename" : "Accessibility-B389.strings",
        "language" : "ms"
      },
      {
        "target" : "Föremål inom räckhåll",
        "filename" : "Accessibility-B389.strings",
        "language" : "sv"
      },
      {
        "target" : "Předmět v dosahu",
        "filename" : "Accessibility-B389.strings",
        "language" : "cs"
      },
      {
        "target" : "손이 닿는 범위 내의 물품",
        "filename" : "Accessibility-B389.strings",
        "language" : "ko"
      },
      {
        "target" : "Objekt innen rekkevidde",
        "filename" : "Accessibility-B389.strings",
        "language" : "no"
      },
      {
        "target" : "Elem elérhető közelségben",
        "filename" : "Accessibility-B389.strings",
        "language" : "hu"
      },
      {
        "target" : "伸手可及的物品",
        "filename" : "Accessibility-B389.strings",
        "language" : "zh_HK"
      },
      {
        "target" : "Nesneye erişilebilir",
        "filename" : "Accessibility-B389.strings",
        "language" : "tr"
      },
      {
        "target" : "Przedmiot w zasięgu ręki",
        "filename" : "Accessibility-B389.strings",
        "language" : "pl"
      },
      {
        "target" : "伸手可及的物品",
        "filename" : "Accessibility-B389.strings",
        "language" : "zh_TW"
      },
      {
        "target" : "Item within reach",
        "filename" : "Accessibility-B389.strings",
        "language" : "en_GB"
      },
      {
        "target" : "Vật dụng trong tầm với",
        "filename" : "Accessibility-B389.strings",
        "language" : "vi"
      },
      {
        "target" : "Вещь в пределах досягаемости",
        "filename" : "Accessibility-B389.strings",
        "language" : "ru"
      },
      {
        "target" : "Objet à portée de main",
        "filename" : "Accessibility-B389.strings",
        "language" : "fr_CA"
      },
      {
        "target" : "Élément à portée",
        "filename" : "Accessibility-B389.strings",
        "language" : "fr"
      },
      {
        "target" : "Kohde ulottuvilla",
        "filename" : "Accessibility-B389.strings",
        "language" : "fi"
      },
      {
        "target" : "Barang dalam jangkauan",
        "filename" : "Accessibility-B389.strings",
        "language" : "id"
      },
      {
        "target" : "Object binnen handbereik",
        "filename" : "Accessibility-B389.strings",
        "language" : "nl"
      },
      {
        "target" : "สิ่งของอยู่ในระยะเอื้อมถึง",
        "filename" : "Accessibility-B389.strings",
        "language" : "th"
      },
      {
        "target" : "Item dentro do alcance",
        "filename" : "Accessibility-B389.strings",
        "language" : "pt"
      },
      {
        "target" : "Articol în apropiere",
        "filename" : "Accessibility-B389.strings",
        "language" : "ro"
      },
      {
        "target" : "Predmet u dosegu",
        "filename" : "Accessibility-B389.strings",
        "language" : "hr"
      },
      {
        "target" : "आइटम पहुँच के भीतर",
        "filename" : "Accessibility-B389.strings",
        "language" : "hi"
      },
      {
        "target" : "Objecte a l’abast",
        "filename" : "Accessibility-B389.strings",
        "language" : "ca"
      }
    ],
    "item.in.field.of.vision.mode" : [
      {
        "target" : "Objekt im Blickfeld",
        "filename" : "Accessibility-B389.strings",
        "language" : "de"
      },
      {
        "target" : "הפריט בשדה הראייה",
        "filename" : "Accessibility-B389.strings",
        "language" : "he"
      },
      {
        "target" : "Item within field of vision",
        "filename" : "Accessibility-B389.strings",
        "language" : "en_AU"
      },
      {
        "target" : "عنصر داخل نطاق الرؤية",
        "filename" : "Accessibility-B389.strings",
        "language" : "ar"
      },
      {
        "target" : "Αντικείμενο εντός οπτικού πεδίου",
        "filename" : "Accessibility-B389.strings",
        "language" : "el"
      },
      {
        "target" : "持ち物は見える範囲内にあります",
        "filename" : "Accessibility-B389.strings",
        "language" : "ja"
      },
      {
        "target" : "Item within field of vision",
        "filename" : "Accessibility-B389.strings",
        "language" : "en"
      },
      {
        "target" : "Обʼєкт у полі зору",
        "filename" : "Accessibility-B389.strings",
        "language" : "uk"
      },
      {
        "target" : "Artículo dentro del campo de visión",
        "filename" : "Accessibility-B389.strings",
        "language" : "es_419"
      },
      {
        "target" : "视野内的物品",
        "filename" : "Accessibility-B389.strings",
        "language" : "zh_CN"
      },
      {
        "target" : "Objeto dentro del campo de visión",
        "filename" : "Accessibility-B389.strings",
        "language" : "es"
      },
      {
        "target" : "Genstand indenfor synsfelt",
        "filename" : "Accessibility-B389.strings",
        "language" : "da"
      },
      {
        "target" : "Oggetto dentro al campo visivo",
        "filename" : "Accessibility-B389.strings",
        "language" : "it"
      },
      {
        "target" : "Predmet v zornom poli",
        "filename" : "Accessibility-B389.strings",
        "language" : "sk"
      },
      {
        "target" : "Objeto no campo de visão",
        "filename" : "Accessibility-B389.strings",
        "language" : "pt_PT"
      },
      {
        "target" : "Item di dalam medan penglihatan",
        "filename" : "Accessibility-B389.strings",
        "language" : "ms"
      },
      {
        "target" : "Föremål inom synfältet",
        "filename" : "Accessibility-B389.strings",
        "language" : "sv"
      },
      {
        "target" : "Předmět v zorném poli",
        "filename" : "Accessibility-B389.strings",
        "language" : "cs"
      },
      {
        "target" : "시야 내의 물품",
        "filename" : "Accessibility-B389.strings",
        "language" : "ko"
      },
      {
        "target" : "Objekt innenfor synsfeltet",
        "filename" : "Accessibility-B389.strings",
        "language" : "no"
      },
      {
        "target" : "Elem a látószögön belül",
        "filename" : "Accessibility-B389.strings",
        "language" : "hu"
      },
      {
        "target" : "視線範圍內的物品",
        "filename" : "Accessibility-B389.strings",
        "language" : "zh_HK"
      },
      {
        "target" : "Nesne görüş alanı içinde",
        "filename" : "Accessibility-B389.strings",
        "language" : "tr"
      },
      {
        "target" : "Przedmiot w polu widzenia",
        "filename" : "Accessibility-B389.strings",
        "language" : "pl"
      },
      {
        "target" : "視野內的物品",
        "filename" : "Accessibility-B389.strings",
        "language" : "zh_TW"
      },
      {
        "target" : "Item within field of vision",
        "filename" : "Accessibility-B389.strings",
        "language" : "en_GB"
      },
      {
        "target" : "Vật dụng trong tầm nhìn",
        "filename" : "Accessibility-B389.strings",
        "language" : "vi"
      },
      {
        "target" : "Вещь в поле зрения",
        "filename" : "Accessibility-B389.strings",
        "language" : "ru"
      },
      {
        "target" : "Objet dans le champ de vision",
        "filename" : "Accessibility-B389.strings",
        "language" : "fr_CA"
      },
      {
        "target" : "Élément dans le champ de vision",
        "filename" : "Accessibility-B389.strings",
        "language" : "fr"
      },
      {
        "target" : "Kohde näkökentässä",
        "filename" : "Accessibility-B389.strings",
        "language" : "fi"
      },
      {
        "target" : "Barang di dalam bidang penglihatan",
        "filename" : "Accessibility-B389.strings",
        "language" : "id"
      },
      {
        "target" : "Object binnen gezichtsveld",
        "filename" : "Accessibility-B389.strings",
        "language" : "nl"
      },
      {
        "target" : "สิ่งของอยู่ในระยะการมองเห็น",
        "filename" : "Accessibility-B389.strings",
        "language" : "th"
      },
      {
        "target" : "Item dentro do campo de visão",
        "filename" : "Accessibility-B389.strings",
        "language" : "pt"
      },
      {
        "target" : "Articol în câmpul vizual",
        "filename" : "Accessibility-B389.strings",
        "language" : "ro"
      },
      {
        "target" : "Predmet u vidnom polju",
        "filename" : "Accessibility-B389.strings",
        "language" : "hr"
      },
      {
        "target" : "आइटम दृष्टि क्षेत्र के भीतर",
        "filename" : "Accessibility-B389.strings",
        "language" : "hi"
      },
      {
        "target" : "Objecte dins del camp de visió",
        "filename" : "Accessibility-B389.strings",
        "language" : "ca"
      }
    ],
    "battery-swap-video" : [
      {
        "target" : "Ein Video, das zeigt, wie die Batterie eines AirTag ausgetauscht wird. Drücke mit zwei Fingern auf die Rückseite und drehe sie gegen den Uhrzeigersinn, um die Batterie zu entfernen. Ersetze die Batterie, setze die Abdeckung wieder auf das Gehäuse und drehe sie zum Schließen mit zwei Fingern im Uhrzeigersinn.",
        "filename" : "Accessibility-B389.strings",
        "language" : "de"
      },
      {
        "target" : "סרטון החלפת סוללה של AirTag. יש ללחוץ עם שתי אצבעות על החלק האחורי של ה-AirTag ולסובב בניגוד לכיוון השעון על-מנת להסיר את הסוללה. יש להחליף את הסוללה, להניח חזרה את המכסה ולסובב בכיוון השעון עם שתי אצבעות לסגירה.",
        "filename" : "Accessibility-B389.strings",
        "language" : "he"
      },
      {
        "target" : "Video of replacing the battery of an AirTag. Press down with two fingers on the back of the AirTag and twist anticlockwise to remove the battery. Replace the battery, put the cover back, and twist clockwise with two fingers to close.",
        "filename" : "Accessibility-B389.strings",
        "language" : "en_AU"
      },
      {
        "target" : "فيديو يعرض استبدال بطارية AirTag. اضغط بإصبعين لأسفل على الجزء الخلفي من AirTag ولفّ الغطاء عكس اتجاه عقارب الساعة لإزالة البطارية. استبدل البطارية وأعد الغطاء إلى مكانه ثم لفّه باتجاه عقارب الساعة بإصبعين للإغلاق.",
        "filename" : "Accessibility-B389.strings",
        "language" : "ar"
      },
      {
        "target" : "Βίντεο που δείχνει την αντικατάσταση της μπαταρίας ενός AirTag. Πιέστε προς τα κάτω με δύο δάχτυλα στο πίσω μέρος του AirTag και περιστρέψτε αριστερόστροφα για αφαίρεση της μπαταρίας. Αντικαταστήστε την μπαταρία, τοποθετήστε το κάλυμμα και περιστρέψτε δεξιόστροφα με δύο δάχτυλα για κλείσιμο.",
        "filename" : "Accessibility-B389.strings",
        "language" : "el"
      },
      {
        "target" : "AirTagの電池交換のビデオです。AirTagの背面のカバーを2本の指で強く押して、反時計回りに回して電池を取り出します。電池を交換して、カバーを元に戻し、2本の指で時計回りに回してカバーを閉じます。",
        "filename" : "Accessibility-B389.strings",
        "language" : "ja"
      },
      {
        "target" : "Video of replacing the battery of an AirTag. Press down with two fingers on the back of AirTag and twist counter-clockwise to remove the battery. Replace the battery, put the cover back, and twist clockwise with two fingers to close.",
        "filename" : "Accessibility-B389.strings",
        "language" : "en"
      },
      {
        "target" : "Відео заміни елемента живлення в тегу AirTag. Притисніть двома пальцями задню кришку AirTag і поверніть її проти годинникової стрілки, щоб вийняти елемент живлення. Замініть його, установіть кришку назад і поверніть її двома пальцями за годинниковою стрілкою, щоб закрити.",
        "filename" : "Accessibility-B389.strings",
        "language" : "uk"
      },
      {
        "target" : "Video del proceso de reemplazo de la batería de un AirTag. Presiona con dos dedos en la parte posterior del AirTag y gira a la izquierda para sacar la batería. Reemplaza la batería, vuelve a colocar la tapa y gira a la derecha con dos dedos para cerrarla.",
        "filename" : "Accessibility-B389.strings",
        "language" : "es_419"
      },
      {
        "target" : "更换AirTag电池的视频。双指按下AirTag的背面并逆时针旋转以移除电池。更换电池并放回后盖，然后双指顺时针旋转以合上。",
        "filename" : "Accessibility-B389.strings",
        "language" : "zh_CN"
      },
      {
        "target" : "Vídeo de cómo cambiar la pila de un AirTag. Aprieta y gira hacia la izquierda la parte trasera del AirTag con dos dedos para extraer la pila. Sustitúyela y vuelve a colocar la tapa apretándola y girándola hacia la derecha con dos dedos.",
        "filename" : "Accessibility-B389.strings",
        "language" : "es"
      },
      {
        "target" : "Video, der viser udskiftning af batteriet i et AirTag. Tryk med to fingre på bagsiden af et AirTag, og drej mod uret for at tage batteriet ud. Udskift batteriet, sæt dækslet på igen, og drej med uret med to fingre for at lukke.",
        "filename" : "Accessibility-B389.strings",
        "language" : "da"
      },
      {
        "target" : "Video che mostra la sostituzione della batteria di un AirTag. Premi con due dita sul retro dell'AirTag e ruota in senso antiorario per rimuovere la batteria. Sostituiscila, posiziona di nuovo la copertura e ruota con due dita in senso orario per chiudere.",
        "filename" : "Accessibility-B389.strings",
        "language" : "it"
      },
      {
        "target" : "Video zachytávajúce výmenu batérie v AirTagu. Zatlačením dvomi prstami na zadnú stranu AirTagu a otočením proti smeru pohybu hodinových ručičiek vyberiete batériu. Vymeňte batériu, nasaďte kryt späť a zatvorte ho otočením dvomi prstami v smere pohybu hodinových ručičiek.",
        "filename" : "Accessibility-B389.strings",
        "language" : "sk"
      },
      {
        "target" : "Vídeo que mostra a substituição da pilha de um AirTag. Carregue com dois dedos na parte de trás do AirTag e rode no sentido anti‑horário para retirar a pilha. Troque a pilha, volte a colocar a tampa e rode com dois dedos no sentido horário para fechar.",
        "filename" : "Accessibility-B389.strings",
        "language" : "pt_PT"
      },
      {
        "target" : "Video menggantikan bateri AirTag. Tekan dengan dua jari di bahagian belakang AirTag dan putar lawan arah jam untuk mengeluarkan bateri. Gantikan bateri, letakkan kembali penutup dan putar ikut arah jam dengan dua jari untuk menutup.",
        "filename" : "Accessibility-B389.strings",
        "language" : "ms"
      },
      {
        "target" : "Video av batteribyte i en AirTag. Tryck ned med två fingrar på baksidan av en AirTag och vrid motsols för att ta bort batteriet. Byt ut batteriet, sätt tillbaka locket och stäng genom att vrida medsols med två fingrar.",
        "filename" : "Accessibility-B389.strings",
        "language" : "sv"
      },
      {
        "target" : "Video výměny baterie v AirTagu. Přitlačte dvěma prsty na zadní stranu AirTagu a otáčením proti směru hodinových ručiček baterii vyjměte. Pak vložte novou, vraťte krytku na místo a zajistěte ji otáčením dvěma prsty po směru hodinových ručiček.",
        "filename" : "Accessibility-B389.strings",
        "language" : "cs"
      },
      {
        "target" : "AirTag의 배터리를 교체하는 영상. AirTag의 뒷면을 두 손가락으로 누르고 반시계 방향으로 돌려서 배터리를 제거합니다. 배터리를 교체하고, 덮개를 다시 올린 다음, 두 손가락으로 시계 방향으로 돌려서 닫습니다.",
        "filename" : "Accessibility-B389.strings",
        "language" : "ko"
      },
      {
        "target" : "En video av hvordan du bytter batteri på AirTag. Trykk ned med to fingre på baksiden av AirTag og vri mot klokken for å fjerne batteriet. Sett inn det nye batteriet, sett på plass dekselet og vri med to fingre med klokken for å lukke det.",
        "filename" : "Accessibility-B389.strings",
        "language" : "no"
      },
      {
        "target" : "Videó egy AirTag elemének kicseréléséről. Nyomja le két ujjal az AirTag hátoldalát, és forgassa el a fedelet az óramutató járásával ellentétes irányba az elem eltávolításához. Cserélje ki az elemet, helyezze vissza a fedelet, és forgassa vissza két ujjal az óramutató járásával megegyező irányba a lezárásához.",
        "filename" : "Accessibility-B389.strings",
        "language" : "hu"
      },
      {
        "target" : "更換AirTag電池的影片。用兩指按下AirTag背蓋並逆時針旋轉以移除電池。更換電池後放回背蓋，並用兩指順時針旋轉即可關上。",
        "filename" : "Accessibility-B389.strings",
        "language" : "zh_HK"
      },
      {
        "target" : "AirTag pilini değiştirme videosu. İki parmağınızla AirTag’in arkasına basın ve pili çıkarmak için saat yönünün tersinde çevirin. Pili değiştirin, kapağı geri takın ve kapatmak için iki parmağınızla saat yönünde çevirin.",
        "filename" : "Accessibility-B389.strings",
        "language" : "tr"
      },
      {
        "target" : "Wideo przedstawiające proces wymiany baterii AirTaga. Naciśnij tył AirTaga dwoma palcami i obróć pokrywę komory baterii w lewo, aby ją usunąć. Wymień baterię, załóż pokrywę, a następnie obróć ją dwoma palcami w prawo.",
        "filename" : "Accessibility-B389.strings",
        "language" : "pl"
      },
      {
        "target" : "替換AirTag電池的影片。用兩指往下推AirTag背蓋並逆時針旋轉以拔除電池。替換電池，放回背蓋，並用兩指順時針旋轉以合上。",
        "filename" : "Accessibility-B389.strings",
        "language" : "zh_TW"
      },
      {
        "target" : "Video of replacing the battery of an AirTag. Press down with two fingers on the back of the AirTag and twist anticlockwise to remove the battery. Replace the battery, put the cover back on, and twist clockwise with two fingers to close.",
        "filename" : "Accessibility-B389.strings",
        "language" : "en_GB"
      },
      {
        "target" : "Video minh họa việc thay thế pin của AirTag. Nhấn mặt sau của AirTag xuống bằng hai ngón tay và xoay ngược chiều kim đồng hồ để tháo pin. Thay thế pin, đặt lại nắp đậy và xoay theo chiều kim đồng hồ bằng hai ngón tay để đóng.",
        "filename" : "Accessibility-B389.strings",
        "language" : "vi"
      },
      {
        "target" : "Видео, демонстрирующее замену элемента питания AirTag. Двумя пальцами нажмите на заднюю поверхность AirTag и проверните ее против часовой стрелки, чтобы извлечь элемент питания. Замените его и установите крышку на место, а затем закройте ее, провернув двумя пальцами по часовой стрелке.",
        "filename" : "Accessibility-B389.strings",
        "language" : "ru"
      },
      {
        "target" : "Vidéo du remplacement de la pile d’un AirTag. Avec deux doigts, exercez une pression sur le dos de l’AirTag en le faisant tourner vers la gauche pour retirer la pile. Remplacez la pile, replacez le couvercle arrière, puis faites-le tourner vers la droite avec deux doigts pour le refermer.",
        "filename" : "Accessibility-B389.strings",
        "language" : "fr_CA"
      },
      {
        "target" : "Vidéo du changement de pile d’un AirTag. Appuyez sur le dos de l’AirTag avec deux doigts et faites tourner le cache dans le sens inverse des aiguilles d’une montre. Remplacez la pile, repositionnez le cache et tournez-le dans le sens des aiguilles d’une montre pour fermer l’AirTag.",
        "filename" : "Accessibility-B389.strings",
        "language" : "fr"
      },
      {
        "target" : "Video AirTagin pariston vaihdosta. Poista paristo painamalla AirTagin takaosaa kahdella sormella ja kiertämällä vastapäivään. Aseta uusi paristo, aseta kansi takaisin ja sulje kiertämällä kahdella sormella myötäpäivään.",
        "filename" : "Accessibility-B389.strings",
        "language" : "fi"
      },
      {
        "target" : "Video penggantian baterai AirTag. Tekan dengan dua jari di bagian belakang AirTag dan putar berlawanan arah jarum jam untuk melepas baterai. Ganti baterai, pasang kembali penutup, dan putar searah jarum jam dengan dua jari untuk menutup.",
        "filename" : "Accessibility-B389.strings",
        "language" : "id"
      },
      {
        "target" : "Video over het vervangen van de batterij bij een AirTag. Druk met twee vingers de klep op de achterkant van de AirTag naar beneden en draai linksom om de batterij te verwijderen. Vervang de batterij, zet de klep terug en draai met twee vingers rechtsom om de klep te sluiten.",
        "filename" : "Accessibility-B389.strings",
        "language" : "nl"
      },
      {
        "target" : "ภาพการเปลี่ยนแบตเตอรี่ของ AirTag โดยใช้นิ้วโป้งทั้งสองข้างกดด้านหลังของ AirTag และหมุนทวนเข็มนาฬิกาเพื่อเอาแบตเตอรี่ออก เปลี่ยนแบตเตอรี่ วางฝาครอบลงบนอุปกรณ์ แล้วใช้นิ้วโป้งทั้งสองข้างหมุนตามเข็มนาฬิกาเพื่อปิดฝาครอบ",
        "filename" : "Accessibility-B389.strings",
        "language" : "th"
      },
      {
        "target" : "Vídeo da substituição da pilha de um AirTag. Pressione a traseira do AirTag com dois dedos e gire no sentido anti-horário para remover a pilha. Substitua a pilha, coloque a tampa de volta e gire no sentido horário com dois dedos para fechar.",
        "filename" : "Accessibility-B389.strings",
        "language" : "pt"
      },
      {
        "target" : "Clip video cu înlocuirea bateriei unui AirTag. Apăsați în jos cu două degete pe partea din spate a unui AirTag și răsuciți în sens invers acelor de ceasornic pentru a scoate bateria. Înlocuiți bateria, puneți capacul înapoi și răsuciți cu două degete în sensul acelor de ceasornic pentru a închide.",
        "filename" : "Accessibility-B389.strings",
        "language" : "ro"
      },
      {
        "target" : "Videozapis zamjene baterije AirTaga. Pritisnite s dva prsta po poleđini AirTaga i okrenite ulijevo za vađenje baterije. Zamijenite bateriju, vratite poklopac i okrenite udesno s dva prsta za zatvaranje.",
        "filename" : "Accessibility-B389.strings",
        "language" : "hr"
      },
      {
        "target" : "AirTag की बैटरी बदलने का वीडियो। AirTag के पिछले भाग पर दो उँगलियों से दबाएँ और बैटरी निकालने के लिए घड़ी की विपरीत दिशा में घुमाएँ। बैटरी बदलें, कवर वापस लगाएँ और बंद करने के लिए घड़ी की दिशा में दो उँगलियों से घुमाएँ।",
        "filename" : "Accessibility-B389.strings",
        "language" : "hi"
      },
      {
        "target" : "Vídeo en què es canvia la pila d’un AirTag. Amb dos dits, s’empeny cap avall la tapa posterior de l’AirTag i després es gira en sentit contrari a les agulles del rellotge per treure la pila. Tot seguit, es canvia la pila, es torna a posar la tapa i es gira amb dos dits en el sentit de les agulles del rellotge per tancar.",
        "filename" : "Accessibility-B389.strings",
        "language" : "ca"
      }
    ],
    "item.out.field.of.vision.mode" : [
      {
        "target" : "Objekt außerhalb des Blickfeldes",
        "filename" : "Accessibility-B389.strings",
        "language" : "de"
      },
      {
        "target" : "הפריט מחוץ לשדה הראייה",
        "filename" : "Accessibility-B389.strings",
        "language" : "he"
      },
      {
        "target" : "Item outside field of vision",
        "filename" : "Accessibility-B389.strings",
        "language" : "en_AU"
      },
      {
        "target" : "عنصر خارج نطاق الرؤية",
        "filename" : "Accessibility-B389.strings",
        "language" : "ar"
      },
      {
        "target" : "Αντικείμενο εκτός οπτικού πεδίου",
        "filename" : "Accessibility-B389.strings",
        "language" : "el"
      },
      {
        "target" : "持ち物は見える範囲外にあります",
        "filename" : "Accessibility-B389.strings",
        "language" : "ja"
      },
      {
        "target" : "Item outside field of vision",
        "filename" : "Accessibility-B389.strings",
        "language" : "en"
      },
      {
        "target" : "Обʼєкт поза полем зору",
        "filename" : "Accessibility-B389.strings",
        "language" : "uk"
      },
      {
        "target" : "Artículo fuera del campo de visión",
        "filename" : "Accessibility-B389.strings",
        "language" : "es_419"
      },
      {
        "target" : "视野外的物品",
        "filename" : "Accessibility-B389.strings",
        "language" : "zh_CN"
      },
      {
        "target" : "Objeto fuera del campo de visión",
        "filename" : "Accessibility-B389.strings",
        "language" : "es"
      },
      {
        "target" : "Genstand udenfor synsfelt",
        "filename" : "Accessibility-B389.strings",
        "language" : "da"
      },
      {
        "target" : "Oggetto fuori dal campo visivo",
        "filename" : "Accessibility-B389.strings",
        "language" : "it"
      },
      {
        "target" : "Predmet mimo zorného poľa",
        "filename" : "Accessibility-B389.strings",
        "language" : "sk"
      },
      {
        "target" : "Objeto fora do campo de visão",
        "filename" : "Accessibility-B389.strings",
        "language" : "pt_PT"
      },
      {
        "target" : "Item di luar medan penglihatan",
        "filename" : "Accessibility-B389.strings",
        "language" : "ms"
      },
      {
        "target" : "Föremål utanför synfältet",
        "filename" : "Accessibility-B389.strings",
        "language" : "sv"
      },
      {
        "target" : "Předmět mimo zorné pole",
        "filename" : "Accessibility-B389.strings",
        "language" : "cs"
      },
      {
        "target" : "시야 밖의 물품",
        "filename" : "Accessibility-B389.strings",
        "language" : "ko"
      },
      {
        "target" : "Objekt utenfor synsfeltet",
        "filename" : "Accessibility-B389.strings",
        "language" : "no"
      },
      {
        "target" : "Elem a látószögön kívül",
        "filename" : "Accessibility-B389.strings",
        "language" : "hu"
      },
      {
        "target" : "視線範圍外的物品",
        "filename" : "Accessibility-B389.strings",
        "language" : "zh_HK"
      },
      {
        "target" : "Nesne görüş alanı dışında",
        "filename" : "Accessibility-B389.strings",
        "language" : "tr"
      },
      {
        "target" : "Przedmiot poza polem widzenia",
        "filename" : "Accessibility-B389.strings",
        "language" : "pl"
      },
      {
        "target" : "視野外的物品",
        "filename" : "Accessibility-B389.strings",
        "language" : "zh_TW"
      },
      {
        "target" : "Item outside field of vision",
        "filename" : "Accessibility-B389.strings",
        "language" : "en_GB"
      },
      {
        "target" : "Vật dụng ngoài tầm nhìn",
        "filename" : "Accessibility-B389.strings",
        "language" : "vi"
      },
      {
        "target" : "Вещь вне поля зрения",
        "filename" : "Accessibility-B389.strings",
        "language" : "ru"
      },
      {
        "target" : "Objet hors du champ de vision",
        "filename" : "Accessibility-B389.strings",
        "language" : "fr_CA"
      },
      {
        "target" : "Élément à l’extérieur du champ de vision",
        "filename" : "Accessibility-B389.strings",
        "language" : "fr"
      },
      {
        "target" : "Kohde näkökentän ulkopuolella",
        "filename" : "Accessibility-B389.strings",
        "language" : "fi"
      },
      {
        "target" : "Barang di luar bidang penglihatan",
        "filename" : "Accessibility-B389.strings",
        "language" : "id"
      },
      {
        "target" : "Object buiten gezichtsveld",
        "filename" : "Accessibility-B389.strings",
        "language" : "nl"
      },
      {
        "target" : "สิ่งของอยู่นอกระยะการมองเห็น",
        "filename" : "Accessibility-B389.strings",
        "language" : "th"
      },
      {
        "target" : "Item fora do campo de visão",
        "filename" : "Accessibility-B389.strings",
        "language" : "pt"
      },
      {
        "target" : "Articol în afara câmpului vizual",
        "filename" : "Accessibility-B389.strings",
        "language" : "ro"
      },
      {
        "target" : "Predmet izvan vidnog polja",
        "filename" : "Accessibility-B389.strings",
        "language" : "hr"
      },
      {
        "target" : "आइटम दृष्टि क्षेत्र के बाहर",
        "filename" : "Accessibility-B389.strings",
        "language" : "hi"
      },
      {
        "target" : "Objecte fora del camp de visió",
        "filename" : "Accessibility-B389.strings",
        "language" : "ca"
      }
    ],
    "calibrating.mode" : [
      {
        "target" : "Kalibrieren …",
        "filename" : "Accessibility-B389.strings",
        "language" : "de"
      },
      {
        "target" : "כיול",
        "filename" : "Accessibility-B389.strings",
        "language" : "he"
      },
      {
        "target" : "Calibrating",
        "filename" : "Accessibility-B389.strings",
        "language" : "en_AU"
      },
      {
        "target" : "تجري المعايرة",
        "filename" : "Accessibility-B389.strings",
        "language" : "ar"
      },
      {
        "target" : "Διακρίβωση…",
        "filename" : "Accessibility-B389.strings",
        "language" : "el"
      },
      {
        "target" : "調整中",
        "filename" : "Accessibility-B389.strings",
        "language" : "ja"
      },
      {
        "target" : "Calibrating",
        "filename" : "Accessibility-B389.strings",
        "language" : "en"
      },
      {
        "target" : "Калібрування",
        "filename" : "Accessibility-B389.strings",
        "language" : "uk"
      },
      {
        "target" : "Calibrando",
        "filename" : "Accessibility-B389.strings",
        "language" : "es_419"
      },
      {
        "target" : "正在校准",
        "filename" : "Accessibility-B389.strings",
        "language" : "zh_CN"
      },
      {
        "target" : "Calibrando",
        "filename" : "Accessibility-B389.strings",
        "language" : "es"
      },
      {
        "target" : "Kalibrerer",
        "filename" : "Accessibility-B389.strings",
        "language" : "da"
      },
      {
        "target" : "Calibrazione in corso",
        "filename" : "Accessibility-B389.strings",
        "language" : "it"
      },
      {
        "target" : "Kalibrujem",
        "filename" : "Accessibility-B389.strings",
        "language" : "sk"
      },
      {
        "target" : "A calibrar",
        "filename" : "Accessibility-B389.strings",
        "language" : "pt_PT"
      },
      {
        "target" : "Mengkalibrasi",
        "filename" : "Accessibility-B389.strings",
        "language" : "ms"
      },
      {
        "target" : "Kalibrering",
        "filename" : "Accessibility-B389.strings",
        "language" : "sv"
      },
      {
        "target" : "Kalibrace",
        "filename" : "Accessibility-B389.strings",
        "language" : "cs"
      },
      {
        "target" : "조정",
        "filename" : "Accessibility-B389.strings",
        "language" : "ko"
      },
      {
        "target" : "Kalibrerer",
        "filename" : "Accessibility-B389.strings",
        "language" : "no"
      },
      {
        "target" : "Kalibrálás",
        "filename" : "Accessibility-B389.strings",
        "language" : "hu"
      },
      {
        "target" : "校正中",
        "filename" : "Accessibility-B389.strings",
        "language" : "zh_HK"
      },
      {
        "target" : "Ayarlanıyor",
        "filename" : "Accessibility-B389.strings",
        "language" : "tr"
      },
      {
        "target" : "Kalibruję",
        "filename" : "Accessibility-B389.strings",
        "language" : "pl"
      },
      {
        "target" : "校正中",
        "filename" : "Accessibility-B389.strings",
        "language" : "zh_TW"
      },
      {
        "target" : "Calibrating",
        "filename" : "Accessibility-B389.strings",
        "language" : "en_GB"
      },
      {
        "target" : "Hiệu chỉnh",
        "filename" : "Accessibility-B389.strings",
        "language" : "vi"
      },
      {
        "target" : "Калибровка",
        "filename" : "Accessibility-B389.strings",
        "language" : "ru"
      },
      {
        "target" : "Étalonnage",
        "filename" : "Accessibility-B389.strings",
        "language" : "fr_CA"
      },
      {
        "target" : "Étalonnage",
        "filename" : "Accessibility-B389.strings",
        "language" : "fr"
      },
      {
        "target" : "Kalibroidaan",
        "filename" : "Accessibility-B389.strings",
        "language" : "fi"
      },
      {
        "target" : "Mengalibrasi",
        "filename" : "Accessibility-B389.strings",
        "language" : "id"
      },
      {
        "target" : "Kalibreren",
        "filename" : "Accessibility-B389.strings",
        "language" : "nl"
      },
      {
        "target" : "กำลังปรับเทียบ",
        "filename" : "Accessibility-B389.strings",
        "language" : "th"
      },
      {
        "target" : "Calibrando",
        "filename" : "Accessibility-B389.strings",
        "language" : "pt"
      },
      {
        "target" : "Calibrare",
        "filename" : "Accessibility-B389.strings",
        "language" : "ro"
      },
      {
        "target" : "Kalibriranje",
        "filename" : "Accessibility-B389.strings",
        "language" : "hr"
      },
      {
        "target" : "कैलिब्रेट किया जा रहा है",
        "filename" : "Accessibility-B389.strings",
        "language" : "hi"
      },
      {
        "target" : "Calibrant",
        "filename" : "Accessibility-B389.strings",
        "language" : "ca"
      }
    ],
    "pairing.loop.video" : [
      {
        "target" : "Eine Animation mit einer Lupe, die über Objekten im Hintergrund schwebt",
        "filename" : "Accessibility-B389.strings",
        "language" : "de"
      },
      {
        "target" : "הנפשה של זכוכית מגדלת המרחפת מעל פריטים ברקע",
        "filename" : "Accessibility-B389.strings",
        "language" : "he"
      },
      {
        "target" : "An animation of a magnifying glass hovering over items in the background",
        "filename" : "Accessibility-B389.strings",
        "language" : "en_AU"
      },
      {
        "target" : "رسم متحرك لعدسة مكبرة تحوم فوق عناصر في الخلفية",
        "filename" : "Accessibility-B389.strings",
        "language" : "ar"
      },
      {
        "target" : "Κινούμενη εικόνα ενός μεγεθυντικού φακού που αιωρείται πάνω από αντικείμενα στο παρασκήνιο",
        "filename" : "Accessibility-B389.strings",
        "language" : "el"
      },
      {
        "target" : "持ち物の上に虫眼鏡をかざして見ているアニメーション",
        "filename" : "Accessibility-B389.strings",
        "language" : "ja"
      },
      {
        "target" : "An animation of a magnifying glass hovering over items in the background",
        "filename" : "Accessibility-B389.strings",
        "language" : "en"
      },
      {
        "target" : "Анімація збільшувального скла, що наводиться на обʼєкти на тлі",
        "filename" : "Accessibility-B389.strings",
        "language" : "uk"
      },
      {
        "target" : "Una animación de una lupa desplazándose sobre los elementos del fondo",
        "filename" : "Accessibility-B389.strings",
        "language" : "es_419"
      },
      {
        "target" : "背景中有放大镜在物品上方移动的动画",
        "filename" : "Accessibility-B389.strings",
        "language" : "zh_CN"
      },
      {
        "target" : "Una animación de una lupa pasando por encima de los objetos que están en segundo plano",
        "filename" : "Accessibility-B389.strings",
        "language" : "es"
      },
      {
        "target" : "Animation af et forstørrelsesglas, der holdes over genstande i baggrunden",
        "filename" : "Accessibility-B389.strings",
        "language" : "da"
      },
      {
        "target" : "Animazione di una lente di ingrandimento che si sposta su alcuni oggetti sullo sfondo",
        "filename" : "Accessibility-B389.strings",
        "language" : "it"
      },
      {
        "target" : "Animácia zväčšovacieho skla vznášajúceho sa nad položkami v pozadí",
        "filename" : "Accessibility-B389.strings",
        "language" : "sk"
      },
      {
        "target" : "Animação de uma lupa a passar por cima de elementos em segundo plano",
        "filename" : "Accessibility-B389.strings",
        "language" : "pt_PT"
      },
      {
        "target" : "Animasi kaca pembesar terapung di atas item di latar belakang",
        "filename" : "Accessibility-B389.strings",
        "language" : "ms"
      },
      {
        "target" : "En animering av ett förstoringsglas som svävar över föremål i bakgrunden",
        "filename" : "Accessibility-B389.strings",
        "language" : "sv"
      },
      {
        "target" : "Animace lupy před různými předměty v pozadí",
        "filename" : "Accessibility-B389.strings",
        "language" : "cs"
      },
      {
        "target" : "배경에서 돋보기가 물품 위로 움직이는 영상",
        "filename" : "Accessibility-B389.strings",
        "language" : "ko"
      },
      {
        "target" : "En animasjon av et forstørrelsesglass som søker over objekter i bakgrunnen",
        "filename" : "Accessibility-B389.strings",
        "language" : "no"
      },
      {
        "target" : "Animáció, amelyen egy nagyító van elhelyezve a háttérben lévő elemek felett",
        "filename" : "Accessibility-B389.strings",
        "language" : "hu"
      },
      {
        "target" : "放大鏡在背景物品上方移動的動畫",
        "filename" : "Accessibility-B389.strings",
        "language" : "zh_HK"
      },
      {
        "target" : "Bir büyütecin arka plandaki öğelerin üzerinde tutulmasını gösteren canlandırma",
        "filename" : "Accessibility-B389.strings",
        "language" : "tr"
      },
      {
        "target" : "Animacja przedstawiająca lupę umieszczoną nad rzeczami w tle",
        "filename" : "Accessibility-B389.strings",
        "language" : "pl"
      },
      {
        "target" : "放大鏡於背景物品上方移動的動畫",
        "filename" : "Accessibility-B389.strings",
        "language" : "zh_TW"
      },
      {
        "target" : "An animation of a magnifying glass hovering over items in the background",
        "filename" : "Accessibility-B389.strings",
        "language" : "en_GB"
      },
      {
        "target" : "Một hình động minh họa kính phóng đại đang di chuyển trên các mục trong nền",
        "filename" : "Accessibility-B389.strings",
        "language" : "vi"
      },
      {
        "target" : "Анимация, показывающая наведение лупы на объекты на заднем плане",
        "filename" : "Accessibility-B389.strings",
        "language" : "ru"
      },
      {
        "target" : "Animation d’une loupe au-dessus d’objets en arrière-plan",
        "filename" : "Accessibility-B389.strings",
        "language" : "fr_CA"
      },
      {
        "target" : "Une animation d’une loupe survolant des éléments en arrière-plan",
        "filename" : "Accessibility-B389.strings",
        "language" : "fr"
      },
      {
        "target" : "Animaatio suurennuslasista, joka leijuu taustalla olevien kohteiden päällä",
        "filename" : "Accessibility-B389.strings",
        "language" : "fi"
      },
      {
        "target" : "Animasi kaca pembesar mengapung di atas item di latar belakang",
        "filename" : "Accessibility-B389.strings",
        "language" : "id"
      },
      {
        "target" : "Een animatie van een vergrootglas dat boven onderdelen op de achtergrond zweeft",
        "filename" : "Accessibility-B389.strings",
        "language" : "nl"
      },
      {
        "target" : "ภาพเคลื่อนไหวของแว่นขยายลอยอยู่เหนือสิ่งของที่อยู่ด้านหลัง",
        "filename" : "Accessibility-B389.strings",
        "language" : "th"
      },
      {
        "target" : "Animação de uma lupa passando sobre itens em segundo plano",
        "filename" : "Accessibility-B389.strings",
        "language" : "pt"
      },
      {
        "target" : "Animația unei lupe care planează peste articolele din fundal",
        "filename" : "Accessibility-B389.strings",
        "language" : "ro"
      },
      {
        "target" : "Animacija povećala koje se pomiče iznad stavki u pozadini.",
        "filename" : "Accessibility-B389.strings",
        "language" : "hr"
      },
      {
        "target" : "बैकग्राउंड में आइटम के ऊपर आवर्धक काँच का ऐनिमेशन",
        "filename" : "Accessibility-B389.strings",
        "language" : "hi"
      },
      {
        "target" : "Animació d’una lupa passant per sobre dels ítems del fons",
        "filename" : "Accessibility-B389.strings",
        "language" : "ca"
      }
    ]
  },
  "bundlePath" : "\/System\/iOSSupport\/System\/Library\/AccessibilityBundles\/FindMy.axbundle",
  "framework" : "FindMy.axbundle"
}