{
  "localizations" : {
    "CFBundleDisplayName" : [
      {
        "target" : "Entfernte Verwaltung",
        "filename" : "InfoPlist.strings",
        "language" : "de"
      },
      {
        "target" : "ניהול מרחוק",
        "filename" : "InfoPlist.strings",
        "language" : "he"
      },
      {
        "target" : "Remote Management",
        "filename" : "InfoPlist.strings",
        "language" : "en_AU"
      },
      {
        "target" : "الإدارة عن بُعد",
        "filename" : "InfoPlist.strings",
        "language" : "ar"
      },
      {
        "target" : "Απομακρυσμένη διαχείριση",
        "filename" : "InfoPlist.strings",
        "language" : "el"
      },
      {
        "target" : "リモートマネージメント",
        "filename" : "InfoPlist.strings",
        "language" : "ja"
      },
      {
        "target" : "Remote Management",
        "filename" : "InfoPlist.strings",
        "language" : "en"
      },
      {
        "target" : "Віддалене керування",
        "filename" : "InfoPlist.strings",
        "language" : "uk"
      },
      {
        "target" : "Administración remota",
        "filename" : "InfoPlist.strings",
        "language" : "es_419"
      },
      {
        "target" : "远程管理",
        "filename" : "InfoPlist.strings",
        "language" : "zh_CN"
      },
      {
        "target" : "Gestión remota",
        "filename" : "InfoPlist.strings",
        "language" : "es"
      },
      {
        "target" : "Gerenciamento Remoto",
        "filename" : "InfoPlist.strings",
        "language" : "pt_BR"
      },
      {
        "target" : "Ekstern administration",
        "filename" : "InfoPlist.strings",
        "language" : "da"
      },
      {
        "target" : "Gestione remota",
        "filename" : "InfoPlist.strings",
        "language" : "it"
      },
      {
        "target" : "Vzdialená správa",
        "filename" : "InfoPlist.strings",
        "language" : "sk"
      },
      {
        "target" : "Gestão remota",
        "filename" : "InfoPlist.strings",
        "language" : "pt_PT"
      },
      {
        "target" : "Pengurusan Jauh",
        "filename" : "InfoPlist.strings",
        "language" : "ms"
      },
      {
        "target" : "Fjärrhanterare",
        "filename" : "InfoPlist.strings",
        "language" : "sv"
      },
      {
        "target" : "Vzdálená správa",
        "filename" : "InfoPlist.strings",
        "language" : "cs"
      },
      {
        "target" : "원격 관리",
        "filename" : "InfoPlist.strings",
        "language" : "ko"
      },
      {
        "target" : "Ekstern administrering",
        "filename" : "InfoPlist.strings",
        "language" : "no"
      },
      {
        "target" : "Távoli felügyelet",
        "filename" : "InfoPlist.strings",
        "language" : "hu"
      },
      {
        "target" : "遙距管理",
        "filename" : "InfoPlist.strings",
        "language" : "zh_HK"
      },
      {
        "target" : "Uzaktan Yönetim",
        "filename" : "InfoPlist.strings",
        "language" : "tr"
      },
      {
        "target" : "Zarządzanie zdalne",
        "filename" : "InfoPlist.strings",
        "language" : "pl"
      },
      {
        "target" : "遠端管理",
        "filename" : "InfoPlist.strings",
        "language" : "zh_TW"
      },
      {
        "target" : "Remote Management",
        "filename" : "InfoPlist.strings",
        "language" : "en_GB"
      },
      {
        "target" : "Quản lý từ xa",
        "filename" : "InfoPlist.strings",
        "language" : "vi"
      },
      {
        "target" : "Удаленное управление",
        "filename" : "InfoPlist.strings",
        "language" : "ru"
      },
      {
        "target" : "Gestion à distance",
        "filename" : "InfoPlist.strings",
        "language" : "fr_CA"
      },
      {
        "target" : "Gestion à distance",
        "filename" : "InfoPlist.strings",
        "language" : "fr"
      },
      {
        "target" : "Etähallinta",
        "filename" : "InfoPlist.strings",
        "language" : "fi"
      },
      {
        "target" : "Manajemen Jarak Jauh",
        "filename" : "InfoPlist.strings",
        "language" : "id"
      },
      {
        "target" : "Extern beheer",
        "filename" : "InfoPlist.strings",
        "language" : "nl"
      },
      {
        "target" : "การจัดการระยะไกล",
        "filename" : "InfoPlist.strings",
        "language" : "th"
      },
      {
        "target" : "Administrare la distanță",
        "filename" : "InfoPlist.strings",
        "language" : "ro"
      },
      {
        "target" : "Daljinsko upravljanje",
        "filename" : "InfoPlist.strings",
        "language" : "hr"
      },
      {
        "target" : "रिमोट प्रबंधन",
        "filename" : "InfoPlist.strings",
        "language" : "hi"
      },
      {
        "target" : "Gestió remota",
        "filename" : "InfoPlist.strings",
        "language" : "ca"
      }
    ],
    "EnableProfileActivity" : [
      {
        "target" : "Profil aktivieren",
        "filename" : "InfoPlist.strings",
        "language" : "de"
      },
      {
        "target" : "הפעל פרופיל",
        "filename" : "InfoPlist.strings",
        "language" : "he"
      },
      {
        "target" : "Enable profile",
        "filename" : "InfoPlist.strings",
        "language" : "en_AU"
      },
      {
        "target" : "تمكين ملف التعريف",
        "filename" : "InfoPlist.strings",
        "language" : "ar"
      },
      {
        "target" : "Ενεργοποίηση προφίλ",
        "filename" : "InfoPlist.strings",
        "language" : "el"
      },
      {
        "target" : "プロファイルを有効にする",
        "filename" : "InfoPlist.strings",
        "language" : "ja"
      },
      {
        "target" : "Enable profile",
        "filename" : "InfoPlist.strings",
        "language" : "en"
      },
      {
        "target" : "Увімкнути профіль",
        "filename" : "InfoPlist.strings",
        "language" : "uk"
      },
      {
        "target" : "Activar perfil",
        "filename" : "InfoPlist.strings",
        "language" : "es_419"
      },
      {
        "target" : "启用描述文件",
        "filename" : "InfoPlist.strings",
        "language" : "zh_CN"
      },
      {
        "target" : "Activar perfil",
        "filename" : "InfoPlist.strings",
        "language" : "es"
      },
      {
        "target" : "Ativar perfil",
        "filename" : "InfoPlist.strings",
        "language" : "pt_BR"
      },
      {
        "target" : "Slå profil til",
        "filename" : "InfoPlist.strings",
        "language" : "da"
      },
      {
        "target" : "Abilita profilo",
        "filename" : "InfoPlist.strings",
        "language" : "it"
      },
      {
        "target" : "Zapnúť profil",
        "filename" : "InfoPlist.strings",
        "language" : "sk"
      },
      {
        "target" : "Ativar perfil",
        "filename" : "InfoPlist.strings",
        "language" : "pt_PT"
      },
      {
        "target" : "Dayakan profil",
        "filename" : "InfoPlist.strings",
        "language" : "ms"
      },
      {
        "target" : "Aktivera profil",
        "filename" : "InfoPlist.strings",
        "language" : "sv"
      },
      {
        "target" : "Aktivovat profil",
        "filename" : "InfoPlist.strings",
        "language" : "cs"
      },
      {
        "target" : "프로파일 활성화",
        "filename" : "InfoPlist.strings",
        "language" : "ko"
      },
      {
        "target" : "Aktiver profil",
        "filename" : "InfoPlist.strings",
        "language" : "no"
      },
      {
        "target" : "A profil engedélyezése",
        "filename" : "InfoPlist.strings",
        "language" : "hu"
      },
      {
        "target" : "啟用描述檔",
        "filename" : "InfoPlist.strings",
        "language" : "zh_HK"
      },
      {
        "target" : "Profili etkinleştir",
        "filename" : "InfoPlist.strings",
        "language" : "tr"
      },
      {
        "target" : "Włącz profil",
        "filename" : "InfoPlist.strings",
        "language" : "pl"
      },
      {
        "target" : "啟用描述檔",
        "filename" : "InfoPlist.strings",
        "language" : "zh_TW"
      },
      {
        "target" : "Enable profile",
        "filename" : "InfoPlist.strings",
        "language" : "en_GB"
      },
      {
        "target" : "Bật hồ sơ",
        "filename" : "InfoPlist.strings",
        "language" : "vi"
      },
      {
        "target" : "Включить профиль",
        "filename" : "InfoPlist.strings",
        "language" : "ru"
      },
      {
        "target" : "Activer le profil",
        "filename" : "InfoPlist.strings",
        "language" : "fr_CA"
      },
      {
        "target" : "Activer le profil",
        "filename" : "InfoPlist.strings",
        "language" : "fr"
      },
      {
        "target" : "Ota profiili käyttöön",
        "filename" : "InfoPlist.strings",
        "language" : "fi"
      },
      {
        "target" : "Aktifkan profil",
        "filename" : "InfoPlist.strings",
        "language" : "id"
      },
      {
        "target" : "Activeer profiel",
        "filename" : "InfoPlist.strings",
        "language" : "nl"
      },
      {
        "target" : "เปิดใช้งานโปรไฟล์",
        "filename" : "InfoPlist.strings",
        "language" : "th"
      },
      {
        "target" : "Activați profilul",
        "filename" : "InfoPlist.strings",
        "language" : "ro"
      },
      {
        "target" : "Omogući profil",
        "filename" : "InfoPlist.strings",
        "language" : "hr"
      },
      {
        "target" : "प्रोफ़ाइल सक्षम करें",
        "filename" : "InfoPlist.strings",
        "language" : "hi"
      },
      {
        "target" : "Activar el perfil",
        "filename" : "InfoPlist.strings",
        "language" : "ca"
      }
    ]
  },
  "bundlePath" : "\/System\/Library\/PrivateFrameworks\/RemoteManagement.framework\/PlugIns\/InteractiveLegacyProfilesExtension.appex",
  "framework" : "InteractiveLegacyProfilesExtension.appex"
}